Workbook
Name NativeTimeline_Join_Date: #N/A
Name Slicer_Age_Group: #N/A
Name Slicer_Country: #N/A
Name Slicer_Favorite_Genre: #N/A
Name Slicer_Price_Tier: #N/A

Sheet streaming_service_data - 
A1: User_ID | B1: User_Name | C1: Join_Date | D1: Last_Login | E1: Monthly_Price | F1: Watch_Hours | G1: Favorite_Genre | H1: Active_Devices | I1: Profile_Count | J1: Parental_Controls | K1: Total_Movies_Watched | L1: Total_Series_Watched | M1: Country | N1: Payment_Method | O1: Language_Preference | P1: Recommended_Content_Count | Q1: Average_Rating_Given | R1: Has_Downloaded_Content | S1: Membership_Status | T1: Loyalty_Points | U1: First_Device_Used | V1: Age_Group | W1: Primary_Watch_Time
A2: 2518 | B2: Amber | C2: 5/15/2023 | D2: 12/13/2024 | E2: 7.99 | F2: 49 | G2: Action | H2: 3 | I2: 6 | J2: TRUE | K2: 641 | L2: 117 | M2: USA | N2: PayPal | O2: Hindi | P2: 84 | Q2: 3.3 | R2: FALSE | S2: Active | T2: 2878 | U2: Smartphone | V2: 35-44 | W2: Late Night
A3: 6430 | B3: Patrick | C3: 44989 | D3: 12/15/2024 | E3: 7.99 | F3: 161 | G3: Drama | H3: 1 | I3: 2 | J3: TRUE | K3: 192 | L3: 65 | M3: USA | N3: PayPal | O3: German | P3: 69 | Q3: 4 | R3: FALSE | S3: Active | T3: 2291 | U3: Desktop | V3: 25-34 | W3: Evening
A4: 1798 | B4: Robert | C4: 44965 | D4: 12/14/2024 | E4: 11.99 | F4: 87 | G4: Action | H4: 2 | I4: 5 | J4: FALSE | K4: 260 | L4: 127 | M4: Canada | N4: Debit Card | O4: Mandarin | P4: 56 | Q4: 3.1 | R4: FALSE | S4: Active | T4: 1692 | U4: Desktop | V4: 35-44 | W4: Late Night
A5: 5255 | B5: Cole | C5: 1/31/2023 | D5: 45334 | E5: 15.99 | F5: 321 | G5: Sci-Fi | H5: 1 | I5: 5 | J5: FALSE | K5: 61 | L5: 192 | M5: UK | N5: Debit Card | O5: Mandarin | P5: 47 | Q5: 4.6 | R5: FALSE | S5: Active | T5: 952 | U5: Desktop | V5: 25-34 | W5: Evening
A6: 2854 | B6: Jamie | C6: 45083 | D6: 12/15/2024 | E6: 11.99 | F6: 386 | G6: Documentary | H6: 1 | I6: 4 | J6: TRUE | K6: 230 | L6: 2 | M6: USA | N6: PayPal | O6: Mandarin | P6: 39 | Q6: 3.7 | R6: FALSE | S6: Active | T6: 1823 | U6: Desktop | V6: 25-34 | W6: Late Night
A7: 6735 | B7: Mary | C7: 9/17/2023 | D7: 11/19/2024 | E7: 15.99 | F7: 408 | G7: Documentary | H7: 2 | I7: 6 | J7: TRUE | K7: 837 | L7: 105 | M7: India | N7: Credit Card | O7: Spanish | P7: 71 | Q7: 4.3 | R7: TRUE | S7: Active | T7: 33 | U7: Smart TV | V7: 18-24 | W7: Morning
A8: 2995 | B8: Theodore | C8: 8/25/2024 | D8: 45577 | E8: 7.99 | F8: 475 | G8: Horror | H8: 5 | I8: 4 | J8: TRUE | K8: 510 | L8: 143 | M8: USA | N8: Credit Card | O8: English | P8: 1 | Q8: 4.5 | R8: FALSE | S8: Active | T8: 755 | U8: Laptop | V8: 35-44 | W8: Late Night
A9: 5120 | B9: Olivia | C9: 5/31/2024 | D9: 12/14/2024 | E9: 15.99 | F9: 258 | G9: Action | H9: 4 | I9: 1 | J9: TRUE | K9: 907 | L9: 47 | M9: Australia | N9: Debit Card | O9: Hindi | P9: 32 | Q9: 3.7 | R9: TRUE | S9: Active | T9: 2866 | U9: Smartphone | V9: 45-54 | W9: Late Night
A10: 6063 | B10: Patricia | C10: 6/17/2023 | D10: 12/17/2024 | E10: 15.99 | F10: 183 | G10: Comedy | H10: 5 | I10: 2 | J10: TRUE | K10: 676 | L10: 61 | M10: Germany | N10: Cryptocurrency | O10: Mandarin | P10: 26 | Q10: 3.3 | R10: TRUE | S10: Active | T10: 336 | U10: Tablet | V10: 25-34 | W10: Late Night
A11: 6896 | B11: Linda | C11: 44969 | D11: 12/14/2024 | E11: 7.99 | F11: 164 | G11: Documentary | H11: 5 | I11: 4 | J11: TRUE | K11: 406 | L11: 79 | M11: USA | N11: Credit Card | O11: French | P11: 90 | Q11: 3.2 | R11: FALSE | S11: Active | T11: 3898 | U11: Laptop | V11: 55+ | W11: Late Night
A12: 8447 | B12: Nichole | C12: 3/28/2023 | D12: 11/22/2024 | E12: 11.99 | F12: 411 | G12: Comedy | H12: 5 | I12: 4 | J12: TRUE | K12: 352 | L12: 78 | M12: UK | N12: Credit Card | O12: English | P12: 47 | Q12: 3.7 | R12: FALSE | S12: Active | T12: 650 | U12: Tablet | V12: 55+ | W12: Late Night
A13: 1433 | B13: Frances | C13: 45325 | D13: 11/20/2024 | E13: 15.99 | F13: 160 | G13: Drama | H13: 5 | I13: 6 | J13: TRUE | K13: 391 | L13: 132 | M13: Canada | N13: Debit Card | O13: German | P13: 57 | Q13: 3 | R13: FALSE | S13: Active | T13: 185 | U13: Laptop | V13: 35-44 | W13: Late Night
A14: 4511 | B14: Maurice | C14: 3/27/2023 | D14: 11/25/2024 | E14: 7.99 | F14: 348 | G14: Drama | H14: 2 | I14: 5 | J14: FALSE | K14: 501 | L14: 71 | M14: Germany | N14: Debit Card | O14: French | P14: 38 | Q14: 4.3 | R14: FALSE | S14: Active | T14: 1547 | U14: Smartphone | V14: 45-54 | W14: Late Night
A15: 9966 | B15: Jennifer | C15: 9/15/2024 | D15: 11/30/2024 | E15: 7.99 | F15: 451 | G15: Documentary | H15: 3 | I15: 1 | J15: FALSE | K15: 995 | L15: 164 | M15: UK | N15: Cryptocurrency | O15: English | P15: 62 | Q15: 3 | R15: TRUE | S15: Active | T15: 3788 | U15: Smartphone | V15: 18-24 | W15: Late Night
A16: 7093 | B16: Cheryl | C16: 45113 | D16: 45608 | E16: 7.99 | F16: 69 | G16: Documentary | H16: 2 | I16: 5 | J16: FALSE | K16: 222 | L16: 13 | M16: France | N16: PayPal | O16: German | P16: 0 | Q16: 4.7 | R16: TRUE | S16: Active | T16: 1051 | U16: Desktop | V16: 18-24 | W16: Afternoon
A17: 4351 | B17: Kathy | C17: 5/18/2024 | D17: 11/30/2024 | E17: 11.99 | F17: 166 | G17: Horror | H17: 1 | I17: 6 | J17: TRUE | K17: 788 | L17: 31 | M17: USA | N17: PayPal | O17: German | P17: 25 | Q17: 4.3 | R17: TRUE | S17: Active | T17: 633 | U17: Smart TV | V17: 35-44 | W17: Afternoon
A18: 6007 | B18: Cassie | C18: 2/14/2023 | D18: 12/17/2024 | E18: 7.99 | F18: 449 | G18: Horror | H18: 2 | I18: 4 | J18: TRUE | K18: 369 | L18: 25 | M18: Germany | N18: Debit Card | O18: Spanish | P18: 65 | Q18: 4.6 | R18: FALSE | S18: Active | T18: 4133 | U18: Smartphone | V18: 25-34 | W18: Evening
A19: 9710 | B19: Charles | C19: 44963 | D19: 11/27/2024 | E19: 7.99 | F19: 441 | G19: Romance | H19: 1 | I19: 5 | J19: FALSE | K19: 228 | L19: 39 | M19: Germany | N19: PayPal | O19: Mandarin | P19: 50 | Q19: 3.1 | R19: TRUE | S19: Active | T19: 1159 | U19: Desktop | V19: 35-44 | W19: Morning
A20: 9034 | B20: William | C20: 9/20/2023 | D20: 12/18/2024 | E20: 15.99 | F20: 224 | G20: Comedy | H20: 1 | I20: 5 | J20: TRUE | K20: 827 | L20: 138 | M20: Canada | N20: Debit Card | O20: Mandarin | P20: 11 | Q20: 4.5 | R20: TRUE | S20: Active | T20: 4673 | U20: Tablet | V20: 18-24 | W20: Afternoon
A21: 6197 | B21: Tiffany | C21: 44992 | D21: 11/28/2024 | E21: 15.99 | F21: 44 | G21: Action | H21: 2 | I21: 4 | J21: FALSE | K21: 983 | L21: 145 | M21: India | N21: PayPal | O21: French | P21: 78 | Q21: 3 | R21: FALSE | S21: Active | T21: 4200 | U21: Laptop | V21: 45-54 | W21: Evening
A22: 2820 | B22: Mark | C22: 7/15/2023 | D22: 45303 | E22: 7.99 | F22: 202 | G22: Drama | H22: 1 | I22: 5 | J22: TRUE | K22: 109 | L22: 41 | M22: USA | N22: Cryptocurrency | O22: Spanish | P22: 42 | Q22: 4.6 | R22: FALSE | S22: Active | T22: 3607 | U22: Desktop | V22: 35-44 | W22: Late Night
A23: 1101 | B23: Mary | C23: 6/13/2024 | D23: 11/23/2024 | E23: 15.99 | F23: 39 | G23: Horror | H23: 2 | I23: 3 | J23: TRUE | K23: 181 | L23: 128 | M23: Australia | N23: PayPal | O23: Mandarin | P23: 3 | Q23: 4.5 | R23: TRUE | S23: Active | T23: 4602 | U23: Smart TV | V23: 55+ | W23: Evening
A24: 1650 | B24: Charles | C24: 8/25/2024 | D24: 11/23/2024 | E24: 15.99 | F24: 319 | G24: Romance | H24: 2 | I24: 2 | J24: FALSE | K24: 842 | L24: 145 | M24: France | N24: Cryptocurrency | O24: Mandarin | P24: 27 | Q24: 3.6 | R24: TRUE | S24: Active | T24: 256 | U24: Smart TV | V24: 35-44 | W24: Afternoon
A25: 4884 | B25: Anne | C25: 11/19/2023 | D25: 11/25/2024 | E25: 15.99 | F25: 150 | G25: Sci-Fi | H25: 3 | I25: 3 | J25: TRUE | K25: 40 | L25: 196 | M25: Canada | N25: Debit Card | O25: German | P25: 60 | Q25: 3.7 | R25: FALSE | S25: Active | T25: 2406 | U25: Laptop | V25: 55+ | W25: Evening
A26: 8321 | B26: Carol | C26: 9/22/2023 | D26: 11/23/2024 | E26: 11.99 | F26: 496 | G26: Romance | H26: 3 | I26: 1 | J26: TRUE | K26: 431 | L26: 41 | M26: India | N26: Credit Card | O26: English | P26: 91 | Q26: 4 | R26: TRUE | S26: Active | T26: 1394 | U26: Smart TV | V26: 55+ | W26: Afternoon
A27: 2381 | B27: Cynthia | C27: 5/15/2024 | D27: 12/15/2024 | E27: 7.99 | F27: 347 | G27: Horror | H27: 2 | I27: 5 | J27: FALSE | K27: 415 | L27: 194 | M27: USA | N27: Credit Card | O27: German | P27: 76 | Q27: 4.3 | R27: TRUE | S27: Active | T27: 1856 | U27: Desktop | V27: 18-24 | W27: Afternoon
A28: 9507 | B28: Destiny | C28: 6/19/2023 | D28: 11/19/2024 | E28: 11.99 | F28: 201 | G28: Action | H28: 1 | I28: 6 | J28: TRUE | K28: 902 | L28: 86 | M28: USA | N28: Cryptocurrency | O28: French | P28: 69 | Q28: 4.9 | R28: TRUE | S28: Active | T28: 1665 | U28: Smart TV | V28: 18-24 | W28: Afternoon
A29: 2851 | B29: Brittany | C29: 5/22/2024 | D29: 11/23/2024 | E29: 15.99 | F29: 415 | G29: Romance | H29: 3 | I29: 5 | J29: TRUE | K29: 769 | L29: 144 | M29: Australia | N29: Cryptocurrency | O29: Spanish | P29: 98 | Q29: 3.9 | R29: FALSE | S29: Active | T29: 2759 | U29: Tablet | V29: 35-44 | W29: Evening
A30: 4083 | B30: Amy | C30: 1/30/2024 | D30: 45577 | E30: 11.99 | F30: 32 | G30: Horror | H30: 1 | I30: 4 | J30: TRUE | K30: 588 | L30: 137 | M30: France | N30: Credit Card | O30: English | P30: 85 | Q30: 3.7 | R30: TRUE | S30: Active | T30: 3433 | U30: Laptop | V30: 35-44 | W30: Afternoon
A31: 4608 | B31: Kimberly | C31: 3/28/2024 | D31: 11/28/2024 | E31: 11.99 | F31: 338 | G31: Comedy | H31: 3 | I31: 2 | J31: TRUE | K31: 528 | L31: 184 | M31: UK | N31: Cryptocurrency | O31: Spanish | P31: 58 | Q31: 3.7 | R31: TRUE | S31: Active | T31: 3966 | U31: Desktop | V31: 55+ | W31: Late Night
A32: 4815 | B32: Ariel | C32: 45329 | D32: 11/20/2024 | E32: 7.99 | F32: 52 | G32: Documentary | H32: 5 | I32: 5 | J32: FALSE | K32: 467 | L32: 23 | M32: USA | N32: PayPal | O32: Spanish | P32: 97 | Q32: 3.3 | R32: TRUE | S32: Active | T32: 4185 | U32: Desktop | V32: 55+ | W32: Evening
A33: 9597 | B33: Lauren | C33: 45455 | D33: 45334 | E33: 11.99 | F33: 447 | G33: Romance | H33: 5 | I33: 5 | J33: FALSE | K33: 73 | L33: 138 | M33: Germany | N33: Debit Card | O33: Hindi | P33: 84 | Q33: 4.1 | R33: FALSE | S33: Active | T33: 784 | U33: Smartphone | V33: 25-34 | W33: Afternoon
A34: 6566 | B34: Joshua | C34: 6/22/2023 | D34: 12/17/2024 | E34: 11.99 | F34: 312 | G34: Horror | H34: 5 | I34: 1 | J34: TRUE | K34: 895 | L34: 154 | M34: Germany | N34: Debit Card | O34: Spanish | P34: 85 | Q34: 4.7 | R34: TRUE | S34: Active | T34: 3428 | U34: Laptop | V34: 25-34 | W34: Evening
A35: 1419 | B35: Megan | C35: 44992 | D35: 12/16/2024 | E35: 11.99 | F35: 406 | G35: Sci-Fi | H35: 2 | I35: 6 | J35: FALSE | K35: 983 | L35: 113 | M35: India | N35: Cryptocurrency | O35: German | P35: 78 | Q35: 3.1 | R35: FALSE | S35: Active | T35: 4245 | U35: Smartphone | V35: 25-34 | W35: Evening
A36: 9470 | B36: Stephanie | C36: 11/28/2023 | D36: 12/15/2024 | E36: 7.99 | F36: 350 | G36: Horror | H36: 3 | I36: 6 | J36: TRUE | K36: 801 | L36: 156 | M36: France | N36: Credit Card | O36: Mandarin | P36: 66 | Q36: 4.6 | R36: TRUE | S36: Active | T36: 2580 | U36: Smart TV | V36: 18-24 | W36: Late Night
A37: 4989 | B37: Terrence | C37: 45566 | D37: 45577 | E37: 7.99 | F37: 99 | G37: Comedy | H37: 2 | I37: 5 | J37: TRUE | K37: 96 | L37: 114 | M37: USA | N37: PayPal | O37: Hindi | P37: 45 | Q37: 4.3 | R37: FALSE | S37: Active | T37: 2779 | U37: Smart TV | V37: 55+ | W37: Morning
A38: 9389 | B38: Julia | C38: 45361 | D38: 11/21/2024 | E38: 15.99 | F38: 53 | G38: Sci-Fi | H38: 1 | I38: 2 | J38: FALSE | K38: 849 | L38: 98 | M38: India | N38: Credit Card | O38: Mandarin | P38: 14 | Q38: 3.1 | R38: FALSE | S38: Active | T38: 2318 | U38: Smartphone | V38: 35-44 | W38: Evening
A39: 7728 | B39: Derrick | C39: 9/15/2023 | D39: 12/13/2024 | E39: 11.99 | F39: 484 | G39: Romance | H39: 3 | I39: 6 | J39: FALSE | K39: 515 | L39: 174 | M39: UK | N39: PayPal | O39: German | P39: 12 | Q39: 4 | R39: TRUE | S39: Active | T39: 827 | U39: Smartphone | V39: 25-34 | W39: Morning
A40: 7943 | B40: Nathan | C40: 45301 | D40: 45303 | E40: 15.99 | F40: 211 | G40: Documentary | H40: 2 | I40: 6 | J40: TRUE | K40: 657 | L40: 137 | M40: Australia | N40: Credit Card | O40: Hindi | P40: 26 | Q40: 4 | R40: TRUE | S40: Active | T40: 2670 | U40: Desktop | V40: 18-24 | W40: Late Night
A41: 2490 | B41: Matthew | C41: 8/18/2023 | D41: 11/19/2024 | E41: 11.99 | F41: 248 | G41: Sci-Fi | H41: 4 | I41: 1 | J41: TRUE | K41: 426 | L41: 21 | M41: India | N41: Debit Card | O41: Spanish | P41: 99 | Q41: 4.8 | R41: FALSE | S41: Active | T41: 2409 | U41: Smartphone | V41: 35-44 | W41: Late Night
A42: 5042 | B42: Ashley | C42: 2/16/2024 | D42: 11/23/2024 | E42: 15.99 | F42: 197 | G42: Romance | H42: 4 | I42: 2 | J42: FALSE | K42: 309 | L42: 178 | M42: Australia | N42: Cryptocurrency | O42: Mandarin | P42: 7 | Q42: 4.3 | R42: FALSE | S42: Active | T42: 1577 | U42: Smart TV | V42: 35-44 | W42: Evening
A43: 3620 | B43: Kerri | C43: 45481 | D43: 45485 | E43: 15.99 | F43: 253 | G43: Comedy | H43: 5 | I43: 5 | J43: TRUE | K43: 141 | L43: 199 | M43: USA | N43: Debit Card | O43: French | P43: 72 | Q43: 3.1 | R43: FALSE | S43: Active | T43: 4072 | U43: Laptop | V43: 45-54 | W43: Afternoon
A44: 8976 | B44: Jessica | C44: 9/17/2024 | D44: 45638 | E44: 7.99 | F44: 352 | G44: Romance | H44: 4 | I44: 3 | J44: TRUE | K44: 112 | L44: 106 | M44: France | N44: Credit Card | O44: French | P44: 33 | Q44: 4.6 | R44: TRUE | S44: Active | T44: 3432 | U44: Tablet | V44: 45-54 | W44: Afternoon
A45: 1570 | B45: Matthew | C45: 7/18/2023 | D45: 11/22/2024 | E45: 11.99 | F45: 97 | G45: Romance | H45: 1 | I45: 2 | J45: FALSE | K45: 836 | L45: 122 | M45: UK | N45: Debit Card | O45: Spanish | P45: 65 | Q45: 4.3 | R45: TRUE | S45: Active | T45: 4511 | U45: Smartphone | V45: 18-24 | W45: Morning
A46: 7709 | B46: Phillip | C46: 45020 | D46: 45303 | E46: 11.99 | F46: 283 | G46: Sci-Fi | H46: 5 | I46: 2 | J46: FALSE | K46: 785 | L46: 1 | M46: Australia | N46: Debit Card | O46: German | P46: 79 | Q46: 3.4 | R46: TRUE | S46: Active | T46: 583 | U46: Tablet | V46: 25-34 | W46: Evening
A47: 9503 | B47: Elizabeth | C47: 45600 | D47: 45424 | E47: 11.99 | F47: 307 | G47: Documentary | H47: 5 | I47: 6 | J47: FALSE | K47: 857 | L47: 9 | M47: France | N47: Cryptocurrency | O47: Hindi | P47: 55 | Q47: 3.2 | R47: TRUE | S47: Active | T47: 3626 | U47: Laptop | V47: 35-44 | W47: Late Night
A48: 9564 | B48: Lisa | C48: 4/26/2023 | D48: 45394 | E48: 15.99 | F48: 203 | G48: Comedy | H48: 5 | I48: 1 | J48: FALSE | K48: 347 | L48: 18 | M48: Australia | N48: Cryptocurrency | O48: Spanish | P48: 8 | Q48: 4.4 | R48: TRUE | S48: Active | T48: 476 | U48: Laptop | V48: 45-54 | W48: Afternoon
A49: 8934 | B49: Natalie | C49: 3/25/2023 | D49: 45424 | E49: 7.99 | F49: 22 | G49: Drama | H49: 4 | I49: 3 | J49: FALSE | K49: 707 | L49: 156 | M49: Canada | N49: Cryptocurrency | O49: Spanish | P49: 99 | Q49: 3.3 | R49: FALSE | S49: Active | T49: 4114 | U49: Desktop | V49: 18-24 | W49: Evening
A50: 1222 | B50: Autumn | C50: 44935 | D50: 45516 | E50: 15.99 | F50: 382 | G50: Romance | H50: 2 | I50: 2 | J50: FALSE | K50: 49 | L50: 45 | M50: Canada | N50: PayPal | O50: Hindi | P50: 63 | Q50: 4 | R50: TRUE | S50: Active | T50: 1581 | U50: Smart TV | V50: 35-44 | W50: Morning
A51: 5762 | B51: James | C51: 3/28/2024 | D51: 45334 | E51: 11.99 | F51: 302 | G51: Comedy | H51: 5 | I51: 4 | J51: FALSE | K51: 801 | L51: 141 | M51: France | N51: Debit Card | O51: Mandarin | P51: 62 | Q51: 3.5 | R51: TRUE | S51: Active | T51: 1293 | U51: Laptop | V51: 45-54 | W51: Morning
A52: 4066 | B52: Jessica | C52: 3/26/2023 | D52: 45638 | E52: 11.99 | F52: 76 | G52: Sci-Fi | H52: 2 | I52: 3 | J52: FALSE | K52: 788 | L52: 55 | M52: UK | N52: Credit Card | O52: German | P52: 50 | Q52: 4.8 | R52: TRUE | S52: Active | T52: 1744 | U52: Laptop | V52: 18-24 | W52: Morning
A53: 6469 | B53: Charles | C53: 6/18/2024 | D53: 11/24/2024 | E53: 11.99 | F53: 125 | G53: Documentary | H53: 3 | I53: 6 | J53: TRUE | K53: 853 | L53: 16 | M53: Australia | N53: PayPal | O53: German | P53: 65 | Q53: 4.8 | R53: TRUE | S53: Active | T53: 448 | U53: Laptop | V53: 18-24 | W53: Late Night
A54: 1364 | B54: Michael | C54: 7/27/2023 | D54: 45334 | E54: 11.99 | F54: 113 | G54: Horror | H54: 1 | I54: 1 | J54: FALSE | K54: 970 | L54: 159 | M54: UK | N54: Credit Card | O54: German | P54: 96 | Q54: 4.9 | R54: TRUE | S54: Active | T54: 3398 | U54: Laptop | V54: 35-44 | W54: Late Night
A55: 4197 | B55: Jessica | C55: 10/31/2024 | D55: 12/13/2024 | E55: 15.99 | F55: 183 | G55: Romance | H55: 3 | I55: 5 | J55: FALSE | K55: 490 | L55: 127 | M55: Canada | N55: Debit Card | O55: Hindi | P55: 40 | Q55: 4.6 | R55: TRUE | S55: Active | T55: 4691 | U55: Desktop | V55: 45-54 | W55: Morning
A56: 9700 | B56: Molly | C56: 12/26/2022 | D56: 11/30/2024 | E56: 15.99 | F56: 272 | G56: Documentary | H56: 5 | I56: 1 | J56: FALSE | K56: 201 | L56: 122 | M56: India | N56: Cryptocurrency | O56: English | P56: 94 | Q56: 4.6 | R56: TRUE | S56: Active | T56: 4674 | U56: Laptop | V56: 45-54 | W56: Afternoon
A57: 5644 | B57: Joshua | C57: 45447 | D57: 45363 | E57: 11.99 | F57: 19 | G57: Comedy | H57: 4 | I57: 2 | J57: TRUE | K57: 741 | L57: 36 | M57: France | N57: PayPal | O57: English | P57: 13 | Q57: 4.4 | R57: FALSE | S57: Active | T57: 3641 | U57: Tablet | V57: 18-24 | W57: Afternoon
A58: 5420 | B58: Lance | C58: 12/31/2022 | D58: 45303 | E58: 11.99 | F58: 204 | G58: Drama | H58: 4 | I58: 6 | J58: FALSE | K58: 928 | L58: 30 | M58: India | N58: Credit Card | O58: Mandarin | P58: 58 | Q58: 4.4 | R58: FALSE | S58: Active | T58: 1765 | U58: Smartphone | V58: 45-54 | W58: Late Night
A59: 7560 | B59: Lori | C59: 12/24/2022 | D59: 45363 | E59: 7.99 | F59: 345 | G59: Horror | H59: 3 | I59: 3 | J59: FALSE | K59: 80 | L59: 100 | M59: USA | N59: Credit Card | O59: Hindi | P59: 40 | Q59: 4.9 | R59: TRUE | S59: Active | T59: 3462 | U59: Smartphone | V59: 55+ | W59: Morning
A60: 9644 | B60: Mark | C60: 45513 | D60: 11/25/2024 | E60: 7.99 | F60: 294 | G60: Comedy | H60: 4 | I60: 1 | J60: TRUE | K60: 453 | L60: 149 | M60: France | N60: PayPal | O60: Hindi | P60: 82 | Q60: 3.9 | R60: TRUE | S60: Active | T60: 790 | U60: Desktop | V60: 18-24 | W60: Morning
A61: 7239 | B61: Jeremy | C61: 12/19/2023 | D61: 11/29/2024 | E61: 15.99 | F61: 318 | G61: Action | H61: 3 | I61: 2 | J61: TRUE | K61: 943 | L61: 116 | M61: Canada | N61: PayPal | O61: Hindi | P61: 22 | Q61: 4.1 | R61: FALSE | S61: Active | T61: 4732 | U61: Laptop | V61: 25-34 | W61: Afternoon
A62: 6415 | B62: Scott | C62: 45270 | D62: 11/19/2024 | E62: 11.99 | F62: 396 | G62: Action | H62: 1 | I62: 2 | J62: FALSE | K62: 348 | L62: 172 | M62: UK | N62: Cryptocurrency | O62: Hindi | P62: 61 | Q62: 3.9 | R62: FALSE | S62: Active | T62: 4599 | U62: Smartphone | V62: 35-44 | W62: Afternoon
A63: 9020 | B63: Sabrina | C63: 44987 | D63: 45363 | E63: 11.99 | F63: 455 | G63: Horror | H63: 5 | I63: 3 | J63: TRUE | K63: 112 | L63: 158 | M63: India | N63: Credit Card | O63: German | P63: 15 | Q63: 3.9 | R63: TRUE | S63: Active | T63: 965 | U63: Smart TV | V63: 25-34 | W63: Morning
A64: 2324 | B64: Zachary | C64: 11/24/2024 | D64: 45608 | E64: 7.99 | F64: 175 | G64: Comedy | H64: 5 | I64: 6 | J64: TRUE | K64: 606 | L64: 195 | M64: USA | N64: Credit Card | O64: English | P64: 95 | Q64: 4 | R64: FALSE | S64: Active | T64: 1155 | U64: Tablet | V64: 35-44 | W64: Late Night
A65: 1354 | B65: Levi | C65: 6/24/2023 | D65: 45485 | E65: 7.99 | F65: 36 | G65: Sci-Fi | H65: 1 | I65: 6 | J65: FALSE | K65: 214 | L65: 114 | M65: India | N65: PayPal | O65: Spanish | P65: 39 | Q65: 4.9 | R65: FALSE | S65: Active | T65: 1110 | U65: Tablet | V65: 18-24 | W65: Afternoon
A66: 4019 | B66: Christine | C66: 12/29/2023 | D66: 45455 | E66: 15.99 | F66: 349 | G66: Documentary | H66: 1 | I66: 6 | J66: TRUE | K66: 334 | L66: 76 | M66: Canada | N66: Credit Card | O66: Mandarin | P66: 32 | Q66: 3.3 | R66: FALSE | S66: Active | T66: 1911 | U66: Smart TV | V66: 55+ | W66: Afternoon
A67: 6178 | B67: Emily | C67: 44929 | D67: 45547 | E67: 11.99 | F67: 262 | G67: Documentary | H67: 5 | I67: 5 | J67: TRUE | K67: 849 | L67: 68 | M67: India | N67: Credit Card | O67: French | P67: 24 | Q67: 3 | R67: FALSE | S67: Active | T67: 1721 | U67: Smartphone | V67: 18-24 | W67: Morning
A68: 8673 | B68: Derrick | C68: 12/29/2023 | D68: 45608 | E68: 7.99 | F68: 378 | G68: Action | H68: 2 | I68: 3 | J68: FALSE | K68: 155 | L68: 69 | M68: UK | N68: Debit Card | O68: Spanish | P68: 11 | Q68: 3.3 | R68: FALSE | S68: Active | T68: 353 | U68: Smart TV | V68: 55+ | W68: Morning
A69: 8250 | B69: Jonathan | C69: 3/15/2024 | D69: 11/29/2024 | E69: 15.99 | F69: 469 | G69: Documentary | H69: 3 | I69: 5 | J69: TRUE | K69: 406 | L69: 71 | M69: Australia | N69: Cryptocurrency | O69: French | P69: 88 | Q69: 4.8 | R69: TRUE | S69: Active | T69: 423 | U69: Tablet | V69: 35-44 | W69: Afternoon
A70: 1609 | B70: David | C70: 4/13/2023 | D70: 12/17/2024 | E70: 7.99 | F70: 87 | G70: Horror | H70: 4 | I70: 4 | J70: FALSE | K70: 571 | L70: 54 | M70: Canada | N70: Credit Card | O70: German | P70: 57 | Q70: 4.2 | R70: FALSE | S70: Active | T70: 344 | U70: Smart TV | V70: 55+ | W70: Morning
A71: 3806 | B71: Gina | C71: 2/19/2023 | D71: 45638 | E71: 15.99 | F71: 471 | G71: Documentary | H71: 3 | I71: 6 | J71: TRUE | K71: 56 | L71: 69 | M71: Canada | N71: PayPal | O71: Mandarin | P71: 44 | Q71: 3.6 | R71: TRUE | S71: Active | T71: 4117 | U71: Tablet | V71: 55+ | W71: Morning
A72: 7973 | B72: Kristin | C72: 45301 | D72: 45363 | E72: 7.99 | F72: 469 | G72: Romance | H72: 5 | I72: 2 | J72: TRUE | K72: 748 | L72: 147 | M72: France | N72: Cryptocurrency | O72: Hindi | P72: 33 | Q72: 4.6 | R72: TRUE | S72: Active | T72: 3983 | U72: Smart TV | V72: 55+ | W72: Evening
A73: 7948 | B73: Douglas | C73: 11/26/2023 | D73: 11/23/2024 | E73: 15.99 | F73: 298 | G73: Sci-Fi | H73: 4 | I73: 1 | J73: FALSE | K73: 603 | L73: 161 | M73: Germany | N73: PayPal | O73: Spanish | P73: 68 | Q73: 4.4 | R73: FALSE | S73: Active | T73: 3941 | U73: Laptop | V73: 35-44 | W73: Afternoon
A74: 3195 | B74: Nicole | C74: 10/13/2023 | D74: 12/17/2024 | E74: 11.99 | F74: 331 | G74: Action | H74: 5 | I74: 5 | J74: FALSE | K74: 990 | L74: 72 | M74: Germany | N74: Debit Card | O74: Spanish | P74: 80 | Q74: 3.7 | R74: FALSE | S74: Active | T74: 3085 | U74: Smartphone | V74: 35-44 | W74: Morning
A75: 6285 | B75: Chloe | C75: 7/31/2023 | D75: 11/30/2024 | E75: 11.99 | F75: 238 | G75: Documentary | H75: 3 | I75: 6 | J75: TRUE | K75: 831 | L75: 101 | M75: USA | N75: PayPal | O75: German | P75: 94 | Q75: 4.4 | R75: TRUE | S75: Active | T75: 48 | U75: Smart TV | V75: 35-44 | W75: Evening
A76: 4303 | B76: David | C76: 45086 | D76: 12/17/2024 | E76: 7.99 | F76: 231 | G76: Comedy | H76: 1 | I76: 4 | J76: FALSE | K76: 420 | L76: 85 | M76: Germany | N76: Cryptocurrency | O76: Mandarin | P76: 30 | Q76: 3.5 | R76: FALSE | S76: Active | T76: 1520 | U76: Smart TV | V76: 55+ | W76: Evening
A77: 7751 | B77: Kevin | C77: 45511 | D77: 11/23/2024 | E77: 11.99 | F77: 457 | G77: Sci-Fi | H77: 2 | I77: 5 | J77: TRUE | K77: 754 | L77: 98 | M77: Canada | N77: PayPal | O77: Mandarin | P77: 53 | Q77: 3.6 | R77: TRUE | S77: Active | T77: 935 | U77: Smartphone | V77: 55+ | W77: Evening
A78: 7813 | B78: Nicholas | C78: 7/20/2024 | D78: 11/21/2024 | E78: 15.99 | F78: 373 | G78: Drama | H78: 4 | I78: 4 | J78: TRUE | K78: 782 | L78: 7 | M78: India | N78: Cryptocurrency | O78: Spanish | P78: 18 | Q78: 3.2 | R78: TRUE | S78: Active | T78: 4641 | U78: Smart TV | V78: 55+ | W78: Evening
A79: 9028 | B79: Terry | C79: 45089 | D79: 11/28/2024 | E79: 15.99 | F79: 11 | G79: Action | H79: 1 | I79: 4 | J79: FALSE | K79: 557 | L79: 165 | M79: USA | N79: PayPal | O79: French | P79: 11 | Q79: 4 | R79: TRUE | S79: Active | T79: 2941 | U79: Smartphone | V79: 25-34 | W79: Late Night
A80: 6109 | B80: Garrett | C80: 10/25/2023 | D80: 45455 | E80: 15.99 | F80: 425 | G80: Romance | H80: 2 | I80: 2 | J80: TRUE | K80: 552 | L80: 27 | M80: Germany | N80: Cryptocurrency | O80: English | P80: 36 | Q80: 4 | R80: TRUE | S80: Active | T80: 1325 | U80: Tablet | V80: 18-24 | W80: Late Night
A81: 2565 | B81: Jose | C81: 9/15/2024 | D81: 12/18/2024 | E81: 7.99 | F81: 231 | G81: Comedy | H81: 5 | I81: 4 | J81: TRUE | K81: 356 | L81: 81 | M81: Australia | N81: Credit Card | O81: French | P81: 73 | Q81: 3.4 | R81: FALSE | S81: Active | T81: 4465 | U81: Tablet | V81: 55+ | W81: Late Night
A82: 7551 | B82: Courtney | C82: 12/31/2023 | D82: 45334 | E82: 15.99 | F82: 483 | G82: Drama | H82: 2 | I82: 4 | J82: FALSE | K82: 161 | L82: 110 | M82: USA | N82: Cryptocurrency | O82: French | P82: 71 | Q82: 4.4 | R82: TRUE | S82: Active | T82: 3517 | U82: Smartphone | V82: 25-34 | W82: Evening
A83: 6398 | B83: Kim | C83: 8/20/2023 | D83: 45485 | E83: 7.99 | F83: 55 | G83: Romance | H83: 3 | I83: 2 | J83: TRUE | K83: 17 | L83: 40 | M83: UK | N83: PayPal | O83: Mandarin | P83: 48 | Q83: 3.7 | R83: FALSE | S83: Active | T83: 1672 | U83: Smart TV | V83: 45-54 | W83: Late Night
A84: 4982 | B84: Katherine | C84: 11/19/2023 | D84: 45638 | E84: 11.99 | F84: 375 | G84: Drama | H84: 4 | I84: 3 | J84: FALSE | K84: 366 | L84: 13 | M84: Canada | N84: PayPal | O84: Hindi | P84: 73 | Q84: 4.8 | R84: TRUE | S84: Active | T84: 2164 | U84: Tablet | V84: 25-34 | W84: Afternoon
A85: 8108 | B85: Lynn | C85: 10/20/2024 | D85: 11/30/2024 | E85: 11.99 | F85: 336 | G85: Comedy | H85: 1 | I85: 2 | J85: FALSE | K85: 758 | L85: 32 | M85: Canada | N85: Cryptocurrency | O85: German | P85: 64 | Q85: 5 | R85: FALSE | S85: Active | T85: 3663 | U85: Smartphone | V85: 18-24 | W85: Evening
A86: 6779 | B86: Leah | C86: 7/22/2024 | D86: 45363 | E86: 7.99 | F86: 196 | G86: Romance | H86: 1 | I86: 6 | J86: TRUE | K86: 936 | L86: 152 | M86: Australia | N86: PayPal | O86: Mandarin | P86: 3 | Q86: 3.1 | R86: TRUE | S86: Active | T86: 2845 | U86: Smartphone | V86: 45-54 | W86: Afternoon
A87: 1169 | B87: Michael | C87: 8/21/2024 | D87: 45363 | E87: 11.99 | F87: 285 | G87: Drama | H87: 3 | I87: 1 | J87: FALSE | K87: 13 | L87: 103 | M87: Australia | N87: Credit Card | O87: Spanish | P87: 11 | Q87: 3.7 | R87: FALSE | S87: Active | T87: 2390 | U87: Laptop | V87: 18-24 | W87: Morning
A88: 5067 | B88: Kayla | C88: 8/31/2024 | D88: 11/27/2024 | E88: 7.99 | F88: 155 | G88: Documentary | H88: 5 | I88: 1 | J88: TRUE | K88: 305 | L88: 77 | M88: USA | N88: Cryptocurrency | O88: French | P88: 66 | Q88: 3.4 | R88: FALSE | S88: Active | T88: 234 | U88: Smartphone | V88: 55+ | W88: Afternoon
A89: 5299 | B89: Katelyn | C89: 4/30/2023 | D89: 45334 | E89: 7.99 | F89: 275 | G89: Comedy | H89: 2 | I89: 2 | J89: TRUE | K89: 755 | L89: 166 | M89: Germany | N89: Debit Card | O89: Mandarin | P89: 45 | Q89: 3.9 | R89: FALSE | S89: Active | T89: 3975 | U89: Tablet | V89: 35-44 | W89: Morning
A90: 3978 | B90: Jessica | C90: 5/15/2024 | D90: 11/28/2024 | E90: 7.99 | F90: 341 | G90: Drama | H90: 3 | I90: 4 | J90: FALSE | K90: 27 | L90: 82 | M90: USA | N90: Debit Card | O90: German | P90: 98 | Q90: 3.7 | R90: TRUE | S90: Active | T90: 561 | U90: Tablet | V90: 45-54 | W90: Afternoon
A91: 8634 | B91: Maria | C91: 44965 | D91: 12/13/2024 | E91: 15.99 | F91: 321 | G91: Drama | H91: 2 | I91: 2 | J91: FALSE | K91: 676 | L91: 81 | M91: USA | N91: Cryptocurrency | O91: English | P91: 65 | Q91: 4.6 | R91: FALSE | S91: Active | T91: 4647 | U91: Tablet | V91: 55+ | W91: Late Night
A92: 9635 | B92: Justin | C92: 12/18/2023 | D92: 11/26/2024 | E92: 11.99 | F92: 456 | G92: Comedy | H92: 2 | I92: 5 | J92: FALSE | K92: 734 | L92: 83 | M92: India | N92: Debit Card | O92: French | P92: 87 | Q92: 3.8 | R92: TRUE | S92: Active | T92: 581 | U92: Tablet | V92: 35-44 | W92: Evening
A93: 1776 | B93: Susan | C93: 10/22/2023 | D93: 11/20/2024 | E93: 15.99 | F93: 15 | G93: Comedy | H93: 1 | I93: 4 | J93: FALSE | K93: 687 | L93: 183 | M93: France | N93: Cryptocurrency | O93: Hindi | P93: 46 | Q93: 4.2 | R93: TRUE | S93: Active | T93: 1250 | U93: Desktop | V93: 55+ | W93: Late Night
A94: 9703 | B94: Mark | C94: 2/29/2024 | D94: 45638 | E94: 11.99 | F94: 410 | G94: Sci-Fi | H94: 3 | I94: 5 | J94: FALSE | K94: 826 | L94: 182 | M94: UK | N94: Cryptocurrency | O94: English | P94: 69 | Q94: 4.2 | R94: FALSE | S94: Active | T94: 3441 | U94: Smartphone | V94: 35-44 | W94: Evening
A95: 3498 | B95: Sue | C95: 45239 | D95: 45303 | E95: 15.99 | F95: 29 | G95: Drama | H95: 2 | I95: 4 | J95: TRUE | K95: 450 | L95: 67 | M95: India | N95: Credit Card | O95: German | P95: 52 | Q95: 3.3 | R95: FALSE | S95: Active | T95: 3211 | U95: Smartphone | V95: 55+ | W95: Morning
A96: 4260 | B96: Jean | C96: 6/24/2024 | D96: 12/16/2024 | E96: 7.99 | F96: 427 | G96: Horror | H96: 1 | I96: 1 | J96: FALSE | K96: 159 | L96: 98 | M96: Germany | N96: Credit Card | O96: Spanish | P96: 66 | Q96: 3.3 | R96: FALSE | S96: Active | T96: 647 | U96: Smartphone | V96: 55+ | W96: Late Night
A97: 7152 | B97: James | C97: 45048 | D97: 45394 | E97: 11.99 | F97: 166 | G97: Action | H97: 5 | I97: 3 | J97: FALSE | K97: 367 | L97: 198 | M97: India | N97: Debit Card | O97: Hindi | P97: 11 | Q97: 4.6 | R97: TRUE | S97: Active | T97: 3751 | U97: Laptop | V97: 35-44 | W97: Afternoon
A98: 2457 | B98: David | C98: 10/21/2023 | D98: 11/26/2024 | E98: 7.99 | F98: 192 | G98: Comedy | H98: 1 | I98: 1 | J98: FALSE | K98: 786 | L98: 140 | M98: Canada | N98: Debit Card | O98: French | P98: 95 | Q98: 3.4 | R98: FALSE | S98: Active | T98: 2925 | U98: Tablet | V98: 25-34 | W98: Late Night
A99: 8530 | B99: Ebony | C99: 3/25/2023 | D99: 45394 | E99: 11.99 | F99: 88 | G99: Documentary | H99: 1 | I99: 6 | J99: TRUE | K99: 962 | L99: 183 | M99: Australia | N99: Debit Card | O99: English | P99: 90 | Q99: 5 | R99: FALSE | S99: Active | T99: 4646 | U99: Smart TV | V99: 55+ | W99: Late Night
A100: 9131 | B100: Derek | C100: 44993 | D100: 11/27/2024 | E100: 7.99 | F100: 127 | G100: Sci-Fi | H100: 2 | I100: 5 | J100: FALSE | K100: 482 | L100: 5 | M100: India | N100: Cryptocurrency | O100: English | P100: 99 | Q100: 3.6 | R100: FALSE | S100: Active | T100: 2867 | U100: Desktop | V100: 25-34 | W100: Afternoon
...

Sheet Data Anomalies -Pls Read It
A2: Notes To Be Focused - Data Anomalies
A4: Error | B4: There are 19 Users above where if you see the Join Date & Last Login shows negative value as the Join date can not be higher than the Last login date
A5: Fixes | B5: Hence I've swapped the last login date and join date to process with report buliding
A7: Error | B7: User ID 4115 - You can see the Join Date & Last Login Date shows the same date, however wathced hours show as 158 which is not technically possible in the real life as 1 day only have 24 hours.
A8: Fixes | B8: I've updated the Last Login date greater by 1 month from Joined Date to process with report building
A10: Notes to be considered - Additional Column Created | P10: Y axis | Q10: Have used this in Heat Map - Just for presentation
P11: 40 | Q11: _40
A12: Sr. No. | B12: Coloumn Name | C12: Logic Used | D12: Fomula Used | P12: 39
A13: 1 | B13: Tenure Days | C13: Last Login - Joined Date | D13: Substraction | P13: 38 | Q13: _38
A14: 2 | B14: Price Tier | C14: Given Names To Subsciption Prices - Basic - 7.99, Standard - 11.99, & Premium - 15.99 | D14: IFS Formula | P14: 37
A15: 3 | B15: Watch HR per Week | C15: Weekly Watching Hours / Weekly Viewing Frequency = (Average Watch Hours normalized by Tenure). | P15: 36 | Q15: _36
A16: 4 | B16: Frequency Bucket | C16: We have used three type of users "Casual" who watch 0-5 hours watch time in a week, "Regular" who watch 5-15 hours watch time in a week & "Power" who watch 15+ hours watch time in a week. | D16: Have used IF formula and above Avg Hrs/WK formula together | P16: 35
A17: 5 | B17: Per Day Watch Hr | C17: Per Day Watching Hours = Watching Hours / Total number of Movies + Total Number of Series | D17: Maths Formula - Divison | E17: This values were not used in report as there was not specific ask in the questions but it can give a good business insights | P17: 34 | Q17: _34
A18: 6 | B18: BR/VW | C18: As We get per day Watch Hour, So have used a logic where if a user is having less than 9 Miutes (0.15 hr) watch time average We've considered it as "Browser" who just comes and check the show and goes back but don't consume the whole content, And second is the "Viewer" who is having more than 9 minutes watch time average Cause that user have spent some time in content consuming. | D18: IFS formula with above Per Day Watch HR | E18: This values were not used in report as there was not specific ask in the questions but it can give a good business insights | P18: 33
P19: 32 | Q19: _32
P20: 31
A21: User_ID | B21: User_Name | C21: Join_Date | D21: Last_Login | E21: Monthly_Price | F21: Watch_Hours | G21: Favorite_Genre | H21: Active_Devices | I21: Profile_Count | J21: Parental_Controls | K21: Total_Movies_Watched | L21: Total_Series_Watched | M21: Country | N21: Payment_Method | O21: Language_Preference | P21: Recommended_Content_Count | Q21: Average_Rating_Given | R21: Has_Downloaded_Content | S21: Membership_Status | T21: Loyalty_Points | U21: First_Device_Used | V21: Age_Group | W21: Primary_Watch_Time | X21: Tenure Days | Y21: Price Tier | Z21: Login Frequence Per Week | AA21: Changes Done
A22: 9597 | B22: Lauren | C22: 45632 | D22: 45628 | E22: 11.99 | F22: 447 | G22: Romance | H22: 5 | I22: 5 | J22: FALSE | K22: 73 | L22: 138 | M22: Germany | N22: Debit Card | O22: Hindi | P22: 84 | Q22: 4.1 | R22: FALSE | S22: Active | T22: 784 | U22: Smartphone | V22: 25-34 | W22: Afternoon | X22: -4 | Y22: STANDARD | Z22: -782.25 | AA22: Swapped Join Date & Last Login Date
A23: 4668 | B23: Carly | C23: 45643 | D23: 45635 | E23: 11.99 | F23: 396 | G23: Sci-Fi | H23: 5 | I23: 5 | J23: TRUE | K23: 549 | L23: 35 | M23: Canada | N23: PayPal | O23: German | P23: 66 | Q23: 3.6 | R23: TRUE | S23: Active | T23: 4293 | U23: Laptop | V23: 55+ | W23: Morning | X23: -8 | Y23: STANDARD | Z23: -346.5 | AA23: Swapped Join Date & Last Login Date
A24: 8068 | B24: Carolyn | C24: 45640 | D24: 45619 | E24: 15.99 | F24: 77 | G24: Drama | H24: 5 | I24: 3 | J24: FALSE | K24: 780 | L24: 138 | M24: India | N24: Cryptocurrency | O24: French | P24: 66 | Q24: 3.4 | R24: FALSE | S24: Active | T24: 1752 | U24: Tablet | V24: 18-24 | W24: Afternoon | X24: -21 | Y24: PREMIUM | Z24: -25.666667 | AA24: Swapped Join Date & Last Login Date
A25: 1003 | B25: Vickie | C25: 45638 | D25: 45618 | E25: 11.99 | F25: 433 | G25: Horror | H25: 5 | I25: 4 | J25: FALSE | K25: 350 | L25: 2 | M25: Germany | N25: Cryptocurrency | O25: Spanish | P25: 41 | Q25: 3.1 | R25: TRUE | S25: Active | T25: 2043 | U25: Smartphone | V25: 35-44 | W25: Late Night | X25: -20 | Y25: STANDARD | Z25: -151.55 | AA25: Swapped Join Date & Last Login Date
A26: 1284 | B26: Michael | C26: 45630 | D26: 45627 | E26: 7.99 | F26: 405 | G26: Comedy | H26: 4 | I26: 3 | J26: TRUE | K26: 695 | L26: 85 | M26: Australia | N26: Credit Card | O26: French | P26: 42 | Q26: 3.7 | R26: FALSE | S26: Active | T26: 2395 | U26: Laptop | V26: 25-34 | W26: Morning | X26: -3 | Y26: BASIC | Z26: -945 | AA26: Swapped Join Date & Last Login Date
A27: 3633 | B27: Randy | C27: 45644 | D27: 45636 | E27: 7.99 | F27: 176 | G27: Action | H27: 5 | I27: 1 | J27: TRUE | K27: 936 | L27: 11 | M27: France | N27: Cryptocurrency | O27: English | P27: 42 | Q27: 3.2 | R27: FALSE | S27: Active | T27: 4414 | U27: Smartphone | V27: 35-44 | W27: Late Night | X27: -8 | Y27: BASIC | Z27: -154 | AA27: Swapped Join Date & Last Login Date
A28: 7484 | B28: Bradley | C28: 45634 | D28: 45617 | E28: 11.99 | F28: 152 | G28: Romance | H28: 5 | I28: 1 | J28: FALSE | K28: 623 | L28: 180 | M28: Canada | N28: Cryptocurrency | O28: French | P28: 89 | Q28: 4.5 | R28: TRUE | S28: Active | T28: 1594 | U28: Smartphone | V28: 25-34 | W28: Late Night | X28: -17 | Y28: STANDARD | Z28: -62.588235 | AA28: Swapped Join Date & Last Login Date
A29: 5083 | B29: Lisa | C29: 45620 | D29: 45619 | E29: 15.99 | F29: 19 | G29: Romance | H29: 3 | I29: 2 | J29: TRUE | K29: 781 | L29: 179 | M29: Canada | N29: Debit Card | O29: German | P29: 8 | Q29: 4.3 | R29: FALSE | S29: Active | T29: 1525 | U29: Laptop | V29: 45-54 | W29: Evening | X29: -1 | Y29: PREMIUM | Z29: -133 | AA29: Swapped Join Date & Last Login Date
A30: 3781 | B30: Jasmine | C30: 45643 | D30: 45625 | E30: 15.99 | F30: 249 | G30: Romance | H30: 1 | I30: 4 | J30: TRUE | K30: 713 | L30: 125 | M30: UK | N30: PayPal | O30: German | P30: 95 | Q30: 4.8 | R30: FALSE | S30: Active | T30: 74 | U30: Laptop | V30: 18-24 | W30: Morning | X30: -18 | Y30: PREMIUM | Z30: -96.833333 | AA30: Swapped Join Date & Last Login Date
A31: 9239 | B31: Daniel | C31: 45621 | D31: 45617 | E31: 15.99 | F31: 274 | G31: Drama | H31: 5 | I31: 6 | J31: FALSE | K31: 732 | L31: 105 | M31: UK | N31: PayPal | O31: Hindi | P31: 36 | Q31: 4.1 | R31: TRUE | S31: Active | T31: 4194 | U31: Smart TV | V31: 45-54 | W31: Evening | X31: -4 | Y31: PREMIUM | Z31: -479.5 | AA31: Swapped Join Date & Last Login Date
A32: 8923 | B32: Douglas | C32: 45637 | D32: 45636 | E32: 11.99 | F32: 100 | G32: Romance | H32: 3 | I32: 4 | J32: FALSE | K32: 417 | L32: 87 | M32: France | N32: Credit Card | O32: English | P32: 14 | Q32: 3.4 | R32: FALSE | S32: Active | T32: 3183 | U32: Smart TV | V32: 35-44 | W32: Afternoon | X32: -1 | Y32: STANDARD | Z32: -700 | AA32: Swapped Join Date & Last Login Date
A33: 1282 | B33: Amy | C33: 45636 | D33: 45623 | E33: 15.99 | F33: 432 | G33: Horror | H33: 4 | I33: 3 | J33: TRUE | K33: 666 | L33: 76 | M33: Australia | N33: Cryptocurrency | O33: French | P33: 92 | Q33: 4.6 | R33: FALSE | S33: Active | T33: 4020 | U33: Tablet | V33: 45-54 | W33: Late Night | X33: -13 | Y33: PREMIUM | Z33: -232.61538 | AA33: Swapped Join Date & Last Login Date
... A40: 4680 | B40: Alexandria | C40: 45642 | D40: 45637 | E40: 11.99 | F40: 221 | G40: Romance | H40: 5 | I40: 5 | J40: TRUE | K40: 749 | L40: 66 | M40: USA | N40: Cryptocurrency | O40: German | P40: 37 | Q40: 3.3 | R40: TRUE | S40: Active | T40: 4505 | U40: Smart TV | V40: 35-44 | W40: Afternoon | X40: -5 | Y40: STANDARD | Z40: -309.4 | AA40: Swapped Join Date & Last Login Date
A41: 4115 | B41: Shawna | C41: 45620 | D41: 45620 | E41: 15.99 | F41: 158 | G41: Comedy | H41: 1 | I41: 5 | J41: TRUE | K41: 603 | L41: 72 | M41: India | N41: Credit Card | O41: Hindi | P41: 88 | Q41: 3.3 | R41: FALSE | S41: Active | T41: 3508 | U41: Smart TV | V41: 55+ | W41: Afternoon | X41: =D41-C41 -> 0 | Y41: {=_xlfn.IFS(E41=7.99,"BASIC",E41=11.99,"STANDARD",E41=15.99,"PREMIUM")} -> PREMIUM | Z41: You can see it's mentioned the hours as 158 but the date is incorrect | AA41: Joined Date & Last Date Was Same So Changed It By One Month

Sheet Cleaned Data
A1: User_ID | B1: User_Name | C1: Join_Date | D1: Last_Login | E1: Monthly_Price | F1: Watch_Hours | G1: Favorite_Genre | H1: Active_Devices | I1: Profile_Count | J1: Parental_Controls | K1: Total_Movies_Watched | L1: Total_Series_Watched | M1: Country | N1: Payment_Method | O1: Language_Preference | P1: Recommended_Content_Count | Q1: Average_Rating_Given | R1: Has_Downloaded_Content | S1: Membership_Status | T1: Loyalty_Points | U1: First_Device_Used | V1: Age_Group | W1: Primary_Watch_Time | X1: Tenure Days | Y1: Price Tier | Z1: Watch HR per Week | AA1: Frequency Bucket | AB1: Per Day Watch Hr | AC1: BR/VW
A2: 2518 | B2: Amber | C2: 45061 | D2: 45639 | E2: 7.99 | F2: 49 | G2: Action | H2: 3 | I2: 6 | J2: TRUE | K2: 641 | L2: 117 | M2: USA | N2: PayPal | O2: Hindi | P2: 84 | Q2: 3.3 | R2: FALSE | S2: Active | T2: 2878 | U2: Smartphone | V2: 35-44 | W2: Late Night | X2: =D2-C2 -> 578 | Y2: {=_xlfn.IFS(E2=7.99,"BASIC",E2=11.99,"STANDARD",E2=15.99,"PREMIUM")} -> BASIC | Z2: =F2/(X2/7) -> 0.59342561 | AA2: {=_xlfn.IFS( (F2/(X2/7)) < 5, "Casual", AND((F2/(X2/7)) >= 5, (F2/(X2/7)) < 15), "Regular", (F2/(X2/7)) >= 15, "Power" )} -> Casual | AB2: =(F2/(K2+L2)) -> 0.064643799 | AC2: =IF(F2/(K2+L2) < 0.15," Browsers","Viewers") -> Browsers
A3: 6430 | B3: Patrick | C3: 45019 | D3: 45641 | E3: 7.99 | F3: 161 | G3: Drama | H3: 1 | I3: 2 | J3: TRUE | K3: 192 | L3: 65 | M3: USA | N3: PayPal | O3: German | P3: 69 | Q3: 4 | R3: FALSE | S3: Active | T3: 2291 | U3: Desktop | V3: 25-34 | W3: Evening | X3: =D3-C3 -> 622 | Y3: {=_xlfn.IFS(E3=7.99,"BASIC",E3=11.99,"STANDARD",E3=15.99,"PREMIUM")} -> BASIC | Z3: =F3/(X3/7) -> 1.8118971 | AA3: {=_xlfn.IFS( (F3/(X3/7)) < 5, "Casual", AND((F3/(X3/7)) >= 5, (F3/(X3/7)) < 15), "Regular", (F3/(X3/7)) >= 15, "Power" )} -> Casual | AB3: =(F3/(K3+L3)) -> 0.62645914 | AC3: =IF(F3/(K3+L3) < 0.15," Browsers","Viewers") -> Viewers
A4: 1798 | B4: Robert | C4: 45140 | D4: 45640 | E4: 11.99 | F4: 87 | G4: Action | H4: 2 | I4: 5 | J4: FALSE | K4: 260 | L4: 127 | M4: Canada | N4: Debit Card | O4: Mandarin | P4: 56 | Q4: 3.1 | R4: FALSE | S4: Active | T4: 1692 | U4: Desktop | V4: 35-44 | W4: Late Night | X4: =D4-C4 -> 500 | Y4: {=_xlfn.IFS(E4=7.99,"BASIC",E4=11.99,"STANDARD",E4=15.99,"PREMIUM")} -> STANDARD | Z4: =F4/(X4/7) -> 1.218 | AA4: {=_xlfn.IFS( (F4/(X4/7)) < 5, "Casual", AND((F4/(X4/7)) >= 5, (F4/(X4/7)) < 15), "Regular", (F4/(X4/7)) >= 15, "Power" )} -> Casual | AB4: =(F4/(K4+L4)) -> 0.2248062 | AC4: =IF(F4/(K4+L4) < 0.15," Browsers","Viewers") -> Viewers
A5: 5255 | B5: Cole | C5: 44957 | D5: 45628 | E5: 15.99 | F5: 321 | G5: Sci-Fi | H5: 1 | I5: 5 | J5: FALSE | K5: 61 | L5: 192 | M5: UK | N5: Debit Card | O5: Mandarin | P5: 47 | Q5: 4.6 | R5: FALSE | S5: Active | T5: 952 | U5: Desktop | V5: 25-34 | W5: Evening | X5: =D5-C5 -> 671 | Y5: {=_xlfn.IFS(E5=7.99,"BASIC",E5=11.99,"STANDARD",E5=15.99,"PREMIUM")} -> PREMIUM | Z5: =F5/(X5/7) -> 3.3487332 | AA5: {=_xlfn.IFS( (F5/(X5/7)) < 5, "Casual", AND((F5/(X5/7)) >= 5, (F5/(X5/7)) < 15), "Regular", (F5/(X5/7)) >= 15, "Power" )} -> Casual | AB5: =(F5/(K5+L5)) -> 1.2687747 | AC5: =IF(F5/(K5+L5) < 0.15," Browsers","Viewers") -> Viewers
A6: 2854 | B6: Jamie | C6: 45083 | D6: 45641 | E6: 11.99 | F6: 386 | G6: Documentary | H6: 1 | I6: 4 | J6: TRUE | K6: 230 | L6: 2 | M6: USA | N6: PayPal | O6: Mandarin | P6: 39 | Q6: 3.7 | R6: FALSE | S6: Active | T6: 1823 | U6: Desktop | V6: 25-34 | W6: Late Night | X6: =D6-C6 -> 558 | Y6: {=_xlfn.IFS(E6=7.99,"BASIC",E6=11.99,"STANDARD",E6=15.99,"PREMIUM")} -> STANDARD | Z6: =F6/(X6/7) -> 4.8422939 | AA6: {=_xlfn.IFS( (F6/(X6/7)) < 5, "Casual", AND((F6/(X6/7)) >= 5, (F6/(X6/7)) < 15), "Regular", (F6/(X6/7)) >= 15, "Power" )} -> Casual | AB6: =(F6/(K6+L6)) -> 1.6637931 | AC6: =IF(F6/(K6+L6) < 0.15," Browsers","Viewers") -> Viewers
A7: 6735 | B7: Mary | C7: 45186 | D7: 45615 | E7: 15.99 | F7: 408 | G7: Documentary | H7: 2 | I7: 6 | J7: TRUE | K7: 837 | L7: 105 | M7: India | N7: Credit Card | O7: Spanish | P7: 71 | Q7: 4.3 | R7: TRUE | S7: Active | T7: 33 | U7: Smart TV | V7: 18-24 | W7: Morning | X7: =D7-C7 -> 429 | Y7: {=_xlfn.IFS(E7=7.99,"BASIC",E7=11.99,"STANDARD",E7=15.99,"PREMIUM")} -> PREMIUM | Z7: =F7/(X7/7) -> 6.6573427 | AA7: {=_xlfn.IFS( (F7/(X7/7)) < 5, "Casual", AND((F7/(X7/7)) >= 5, (F7/(X7/7)) < 15), "Regular", (F7/(X7/7)) >= 15, "Power" )} -> Regular | AB7: =(F7/(K7+L7)) -> 0.43312102 | AC7: =IF(F7/(K7+L7) < 0.15," Browsers","Viewers") -> Viewers
A8: 2995 | B8: Theodore | C8: 45529 | D8: 45636 | E8: 7.99 | F8: 475 | G8: Horror | H8: 5 | I8: 4 | J8: TRUE | K8: 510 | L8: 143 | M8: USA | N8: Credit Card | O8: English | P8: 1 | Q8: 4.5 | R8: FALSE | S8: Active | T8: 755 | U8: Laptop | V8: 35-44 | W8: Late Night | X8: =D8-C8 -> 107 | Y8: {=_xlfn.IFS(E8=7.99,"BASIC",E8=11.99,"STANDARD",E8=15.99,"PREMIUM")} -> BASIC | Z8: =F8/(X8/7) -> 31.074766 | AA8: {=_xlfn.IFS( (F8/(X8/7)) < 5, "Casual", AND((F8/(X8/7)) >= 5, (F8/(X8/7)) < 15), "Regular", (F8/(X8/7)) >= 15, "Power" )} -> Power | AB8: =(F8/(K8+L8)) -> 0.72741194 | AC8: =IF(F8/(K8+L8) < 0.15," Browsers","Viewers") -> Viewers
A9: 5120 | B9: Olivia | C9: 45443 | D9: 45640 | E9: 15.99 | F9: 258 | G9: Action | H9: 4 | I9: 1 | J9: TRUE | K9: 907 | L9: 47 | M9: Australia | N9: Debit Card | O9: Hindi | P9: 32 | Q9: 3.7 | R9: TRUE | S9: Active | T9: 2866 | U9: Smartphone | V9: 45-54 | W9: Late Night | X9: =D9-C9 -> 197 | Y9: {=_xlfn.IFS(E9=7.99,"BASIC",E9=11.99,"STANDARD",E9=15.99,"PREMIUM")} -> PREMIUM | Z9: =F9/(X9/7) -> 9.1675127 | AA9: {=_xlfn.IFS( (F9/(X9/7)) < 5, "Casual", AND((F9/(X9/7)) >= 5, (F9/(X9/7)) < 15), "Regular", (F9/(X9/7)) >= 15, "Power" )} -> Regular | AB9: =(F9/(K9+L9)) -> 0.27044025 | AC9: =IF(F9/(K9+L9) < 0.15," Browsers","Viewers") -> Viewers
A10: 6063 | B10: Patricia | C10: 45094 | D10: 45643 | E10: 15.99 | F10: 183 | G10: Comedy | H10: 5 | I10: 2 | J10: TRUE | K10: 676 | L10: 61 | M10: Germany | N10: Cryptocurrency | O10: Mandarin | P10: 26 | Q10: 3.3 | R10: TRUE | S10: Active | T10: 336 | U10: Tablet | V10: 25-34 | W10: Late Night | X10: =D10-C10 -> 549 | Y10: {=_xlfn.IFS(E10=7.99,"BASIC",E10=11.99,"STANDARD",E10=15.99,"PREMIUM")} -> PREMIUM | Z10: =F10/(X10/7) -> 2.3333333 | AA10: {=_xlfn.IFS( (F10/(X10/7)) < 5, "Casual", AND((F10/(X10/7)) >= 5, (F10/(X10/7)) < 15), "Regular", (F10/(X10/7)) >= 15, "Power" )} -> Casual | AB10: =(F10/(K10+L10)) -> 0.24830393 | AC10: =IF(F10/(K10+L10) < 0.15," Browsers","Viewers") -> Viewers
A11: 6896 | B11: Linda | C11: 45262 | D11: 45640 | E11: 7.99 | F11: 164 | G11: Documentary | H11: 5 | I11: 4 | J11: TRUE | K11: 406 | L11: 79 | M11: USA | N11: Credit Card | O11: French | P11: 90 | Q11: 3.2 | R11: FALSE | S11: Active | T11: 3898 | U11: Laptop | V11: 55+ | W11: Late Night | X11: =D11-C11 -> 378 | Y11: {=_xlfn.IFS(E11=7.99,"BASIC",E11=11.99,"STANDARD",E11=15.99,"PREMIUM")} -> BASIC | Z11: =F11/(X11/7) -> 3.037037 | AA11: {=_xlfn.IFS( (F11/(X11/7)) < 5, "Casual", AND((F11/(X11/7)) >= 5, (F11/(X11/7)) < 15), "Regular", (F11/(X11/7)) >= 15, "Power" )} -> Casual | AB11: =(F11/(K11+L11)) -> 0.33814433 | AC11: =IF(F11/(K11+L11) < 0.15," Browsers","Viewers") -> Viewers
A12: 8447 | B12: Nichole | C12: 45013 | D12: 45618 | E12: 11.99 | F12: 411 | G12: Comedy | H12: 5 | I12: 4 | J12: TRUE | K12: 352 | L12: 78 | M12: UK | N12: Credit Card | O12: English | P12: 47 | Q12: 3.7 | R12: FALSE | S12: Active | T12: 650 | U12: Tablet | V12: 55+ | W12: Late Night | X12: =D12-C12 -> 605 | Y12: {=_xlfn.IFS(E12=7.99,"BASIC",E12=11.99,"STANDARD",E12=15.99,"PREMIUM")} -> STANDARD | Z12: =F12/(X12/7) -> 4.7553719 | AA12: {=_xlfn.IFS( (F12/(X12/7)) < 5, "Casual", AND((F12/(X12/7)) >= 5, (F12/(X12/7)) < 15), "Regular", (F12/(X12/7)) >= 15, "Power" )} -> Casual | AB12: =(F12/(K12+L12)) -> 0.95581395 | AC12: =IF(F12/(K12+L12) < 0.15," Browsers","Viewers") -> Viewers
A13: 1433 | B13: Frances | C13: 45353 | D13: 45616 | E13: 15.99 | F13: 160 | G13: Drama | H13: 5 | I13: 6 | J13: TRUE | K13: 391 | L13: 132 | M13: Canada | N13: Debit Card | O13: German | P13: 57 | Q13: 3 | R13: FALSE | S13: Active | T13: 185 | U13: Laptop | V13: 35-44 | W13: Late Night | X13: =D13-C13 -> 263 | Y13: {=_xlfn.IFS(E13=7.99,"BASIC",E13=11.99,"STANDARD",E13=15.99,"PREMIUM")} -> PREMIUM | Z13: =F13/(X13/7) -> 4.2585551 | AA13: {=_xlfn.IFS( (F13/(X13/7)) < 5, "Casual", AND((F13/(X13/7)) >= 5, (F13/(X13/7)) < 15), "Regular", (F13/(X13/7)) >= 15, "Power" )} -> Casual | AB13: =(F13/(K13+L13)) -> 0.30592734 | AC13: =IF(F13/(K13+L13) < 0.15," Browsers","Viewers") -> Viewers
... A32: 4815 | B32: Ariel | C32: 45475 | D32: 45616 | E32: 7.99 | F32: 52 | G32: Documentary | H32: 5 | I32: 5 | J32: FALSE | K32: 467 | L32: 23 | M32: USA | N32: PayPal | O32: Spanish | P32: 97 | Q32: 3.3 | R32: TRUE | S32: Active | T32: 4185 | U32: Desktop | V32: 55+ | W32: Evening | X32: =D32-C32 -> 141 | Y32: {=_xlfn.IFS(E32=7.99,"BASIC",E32=11.99,"STANDARD",E32=15.99,"PREMIUM")} -> BASIC | Z32: =F32/(X32/7) -> 2.5815603 | AA32: {=_xlfn.IFS( (F32/(X32/7)) < 5, "Casual", AND((F32/(X32/7)) >= 5, (F32/(X32/7)) < 15), "Regular", (F32/(X32/7)) >= 15, "Power" )} -> Casual | AB32: =(F32/(K32+L32)) -> 0.10612245 | AC32: =IF(F32/(K32+L32) < 0.15," Browsers","Viewers") -> Browsers
A33: 9597 | B33: Lauren | C33: =_xlfn.XLOOKUP(A33,'Data Anomalies -Pls Read It'!A:A,'Data Anomalies -Pls Read It'!D:D,1,0) -> 45628 | D33: =_xlfn.XLOOKUP(A33,'Data Anomalies -Pls Read It'!A:A,'Data Anomalies -Pls Read It'!C:C,1,0) -> 45632 | E33: 11.99 | F33: 447 | G33: Romance | H33: 5 | I33: 5 | J33: FALSE | K33: 73 | L33: 138 | M33: Germany | N33: Debit Card | O33: Hindi | P33: 84 | Q33: 4.1 | R33: FALSE | S33: Active | T33: 784 | U33: Smartphone | V33: 25-34 | W33: Afternoon | X33: =D33-C33 -> 4 | Y33: {=_xlfn.IFS(E33=7.99,"BASIC",E33=11.99,"STANDARD",E33=15.99,"PREMIUM")} -> STANDARD | Z33: =F33/(X33/7) -> 782.25 | AA33: {=_xlfn.IFS( (F33/(X33/7)) < 5, "Casual", AND((F33/(X33/7)) >= 5, (F33/(X33/7)) < 15), "Regular", (F33/(X33/7)) >= 15, "Power" )} -> Power | AB33: =(F33/(K33+L33)) -> 2.1184834 | AC33: =IF(F33/(K33+L33) < 0.15," Browsers","Viewers") -> Viewers | AD33: Correction
A34: 6566 | B34: Joshua | C34: 45099 | D34: 45643 | E34: 11.99 | F34: 312 | G34: Horror | H34: 5 | I34: 1 | J34: TRUE | K34: 895 | L34: 154 | M34: Germany | N34: Debit Card | O34: Spanish | P34: 85 | Q34: 4.7 | R34: TRUE | S34: Active | T34: 3428 | U34: Laptop | V34: 25-34 | W34: Evening | X34: =D34-C34 -> 544 | Y34: {=_xlfn.IFS(E34=7.99,"BASIC",E34=11.99,"STANDARD",E34=15.99,"PREMIUM")} -> STANDARD | Z34: =F34/(X34/7) -> 4.0147059 | AA34: {=_xlfn.IFS( (F34/(X34/7)) < 5, "Casual", AND((F34/(X34/7)) >= 5, (F34/(X34/7)) < 15), "Regular", (F34/(X34/7)) >= 15, "Power" )} -> Casual | AB34: =(F34/(K34+L34)) -> 0.29742612 | AC34: =IF(F34/(K34+L34) < 0.15," Browsers","Viewers") -> Viewers
A35: 1419 | B35: Megan | C35: 45110 | D35: 45642 | E35: 11.99 | F35: 406 | G35: Sci-Fi | H35: 2 | I35: 6 | J35: FALSE | K35: 983 | L35: 113 | M35: India | N35: Cryptocurrency | O35: German | P35: 78 | Q35: 3.1 | R35: FALSE | S35: Active | T35: 4245 | U35: Smartphone | V35: 25-34 | W35: Evening | X35: =D35-C35 -> 532 | Y35: {=_xlfn.IFS(E35=7.99,"BASIC",E35=11.99,"STANDARD",E35=15.99,"PREMIUM")} -> STANDARD | Z35: =F35/(X35/7) -> 5.3421053 | AA35: {=_xlfn.IFS( (F35/(X35/7)) < 5, "Casual", AND((F35/(X35/7)) >= 5, (F35/(X35/7)) < 15), "Regular", (F35/(X35/7)) >= 15, "Power" )} -> Regular | AB35: =(F35/(K35+L35)) -> 0.37043796 | AC35: =IF(F35/(K35+L35) < 0.15," Browsers","Viewers") -> Viewers
A36: 9470 | B36: Stephanie | C36: 45258 | D36: 45641 | E36: 7.99 | F36: 350 | G36: Horror | H36: 3 | I36: 6 | J36: TRUE | K36: 801 | L36: 156 | M36: France | N36: Credit Card | O36: Mandarin | P36: 66 | Q36: 4.6 | R36: TRUE | S36: Active | T36: 2580 | U36: Smart TV | V36: 18-24 | W36: Late Night | X36: =D36-C36 -> 383 | Y36: {=_xlfn.IFS(E36=7.99,"BASIC",E36=11.99,"STANDARD",E36=15.99,"PREMIUM")} -> BASIC | Z36: =F36/(X36/7) -> 6.3968668 | AA36: {=_xlfn.IFS( (F36/(X36/7)) < 5, "Casual", AND((F36/(X36/7)) >= 5, (F36/(X36/7)) < 15), "Regular", (F36/(X36/7)) >= 15, "Power" )} -> Regular | AB36: =(F36/(K36+L36)) -> 0.36572623 | AC36: =IF(F36/(K36+L36) < 0.15," Browsers","Viewers") -> Viewers
A37: 4989 | B37: Terrence | C37: 45301 | D37: 45636 | E37: 7.99 | F37: 99 | G37: Comedy | H37: 2 | I37: 5 | J37: TRUE | K37: 96 | L37: 114 | M37: USA | N37: PayPal | O37: Hindi | P37: 45 | Q37: 4.3 | R37: FALSE | S37: Active | T37: 2779 | U37: Smart TV | V37: 55+ | W37: Morning | X37: =D37-C37 -> 335 | Y37: {=_xlfn.IFS(E37=7.99,"BASIC",E37=11.99,"STANDARD",E37=15.99,"PREMIUM")} -> BASIC | Z37: =F37/(X37/7) -> 2.0686567 | AA37: {=_xlfn.IFS( (F37/(X37/7)) < 5, "Casual", AND((F37/(X37/7)) >= 5, (F37/(X37/7)) < 15), "Regular", (F37/(X37/7)) >= 15, "Power" )} -> Casual | AB37: =(F37/(K37+L37)) -> 0.47142857 | AC37: =IF(F37/(K37+L37) < 0.15," Browsers","Viewers") -> Viewers
A38: 9389 | B38: Julia | C38: 45568 | D38: 45617 | E38: 15.99 | F38: 53 | G38: Sci-Fi | H38: 1 | I38: 2 | J38: FALSE | K38: 849 | L38: 98 | M38: India | N38: Credit Card | O38: Mandarin | P38: 14 | Q38: 3.1 | R38: FALSE | S38: Active | T38: 2318 | U38: Smartphone | V38: 35-44 | W38: Evening | X38: =D38-C38 -> 49 | Y38: {=_xlfn.IFS(E38=7.99,"BASIC",E38=11.99,"STANDARD",E38=15.99,"PREMIUM")} -> PREMIUM | Z38: =F38/(X38/7) -> 7.5714286 | AA38: {=_xlfn.IFS( (F38/(X38/7)) < 5, "Casual", AND((F38/(X38/7)) >= 5, (F38/(X38/7)) < 15), "Regular", (F38/(X38/7)) >= 15, "Power" )} -> Regular | AB38: =(F38/(K38+L38)) -> 0.055966209 | AC38: =IF(F38/(K38+L38) < 0.15," Browsers","Viewers") -> Browsers
A39: 7728 | B39: Derrick | C39: 45184 | D39: 45639 | E39: 11.99 | F39: 484 | G39: Romance | H39: 3 | I39: 6 | J39: FALSE | K39: 515 | L39: 174 | M39: UK | N39: PayPal | O39: German | P39: 12 | Q39: 4 | R39: TRUE | S39: Active | T39: 827 | U39: Smartphone | V39: 25-34 | W39: Morning | X39: =D39-C39 -> 455 | Y39: {=_xlfn.IFS(E39=7.99,"BASIC",E39=11.99,"STANDARD",E39=15.99,"PREMIUM")} -> STANDARD | Z39: =F39/(X39/7) -> 7.4461538 | AA39: {=_xlfn.IFS( (F39/(X39/7)) < 5, "Casual", AND((F39/(X39/7)) >= 5, (F39/(X39/7)) < 15), "Regular", (F39/(X39/7)) >= 15, "Power" )} -> Regular | AB39: =(F39/(K39+L39)) -> 0.70246734 | AC39: =IF(F39/(K39+L39) < 0.15," Browsers","Viewers") -> Viewers
A40: 7943 | B40: Nathan | C40: 45566 | D40: 45627 | E40: 15.99 | F40: 211 | G40: Documentary | H40: 2 | I40: 6 | J40: TRUE | K40: 657 | L40: 137 | M40: Australia | N40: Credit Card | O40: Hindi | P40: 26 | Q40: 4 | R40: TRUE | S40: Active | T40: 2670 | U40: Desktop | V40: 18-24 | W40: Late Night | X40: =D40-C40 -> 61 | Y40: {=_xlfn.IFS(E40=7.99,"BASIC",E40=11.99,"STANDARD",E40=15.99,"PREMIUM")} -> PREMIUM | Z40: =F40/(X40/7) -> 24.213115 | AA40: {=_xlfn.IFS( (F40/(X40/7)) < 5, "Casual", AND((F40/(X40/7)) >= 5, (F40/(X40/7)) < 15), "Regular", (F40/(X40/7)) >= 15, "Power" )} -> Power | AB40: =(F40/(K40+L40)) -> 0.26574307 | AC40: =IF(F40/(K40+L40) < 0.15," Browsers","Viewers") -> Viewers
A41: 2490 | B41: Matthew | C41: 45156 | D41: 45615 | E41: 11.99 | F41: 248 | G41: Sci-Fi | H41: 4 | I41: 1 | J41: TRUE | K41: 426 | L41: 21 | M41: India | N41: Debit Card | O41: Spanish | P41: 99 | Q41: 4.8 | R41: FALSE | S41: Active | T41: 2409 | U41: Smartphone | V41: 35-44 | W41: Late Night | X41: =D41-C41 -> 459 | Y41: {=_xlfn.IFS(E41=7.99,"BASIC",E41=11.99,"STANDARD",E41=15.99,"PREMIUM")} -> STANDARD | Z41: =F41/(X41/7) -> 3.7821351 | AA41: {=_xlfn.IFS( (F41/(X41/7)) < 5, "Casual", AND((F41/(X41/7)) >= 5, (F41/(X41/7)) < 15), "Regular", (F41/(X41/7)) >= 15, "Power" )} -> Casual | AB41: =(F41/(K41+L41)) -> 0.55480984 | AC41: =IF(F41/(K41+L41) < 0.15," Browsers","Viewers") -> Viewers
A42: 5042 | B42: Ashley | C42: 45338 | D42: 45619 | E42: 15.99 | F42: 197 | G42: Romance | H42: 4 | I42: 2 | J42: FALSE | K42: 309 | L42: 178 | M42: Australia | N42: Cryptocurrency | O42: Mandarin | P42: 7 | Q42: 4.3 | R42: FALSE | S42: Active | T42: 1577 | U42: Smart TV | V42: 35-44 | W42: Evening | X42: =D42-C42 -> 281 | Y42: {=_xlfn.IFS(E42=7.99,"BASIC",E42=11.99,"STANDARD",E42=15.99,"PREMIUM")} -> PREMIUM | Z42: =F42/(X42/7) -> 4.9074733 | AA42: {=_xlfn.IFS( (F42/(X42/7)) < 5, "Casual", AND((F42/(X42/7)) >= 5, (F42/(X42/7)) < 15), "Regular", (F42/(X42/7)) >= 15, "Power" )} -> Casual | AB42: =(F42/(K42+L42)) -> 0.40451745 | AC42: =IF(F42/(K42+L42) < 0.15," Browsers","Viewers") -> Viewers
A43: 3620 | B43: Kerri | C43: 45511 | D43: 45633 | E43: 15.99 | F43: 253 | G43: Comedy | H43: 5 | I43: 5 | J43: TRUE | K43: 141 | L43: 199 | M43: USA | N43: Debit Card | O43: French | P43: 72 | Q43: 3.1 | R43: FALSE | S43: Active | T43: 4072 | U43: Laptop | V43: 45-54 | W43: Afternoon | X43: =D43-C43 -> 122 | Y43: {=_xlfn.IFS(E43=7.99,"BASIC",E43=11.99,"STANDARD",E43=15.99,"PREMIUM")} -> PREMIUM | Z43: =F43/(X43/7) -> 14.516393 | AA43: {=_xlfn.IFS( (F43/(X43/7)) < 5, "Casual", AND((F43/(X43/7)) >= 5, (F43/(X43/7)) < 15), "Regular", (F43/(X43/7)) >= 15, "Power" )} -> Regular | AB43: =(F43/(K43+L43)) -> 0.74411765 | AC43: =IF(F43/(K43+L43) < 0.15," Browsers","Viewers") -> Viewers
A44: 8976 | B44: Jessica | C44: 45552 | D44: 45638 | E44: 7.99 | F44: 352 | G44: Romance | H44: 4 | I44: 3 | J44: TRUE | K44: 112 | L44: 106 | M44: France | N44: Credit Card | O44: French | P44: 33 | Q44: 4.6 | R44: TRUE | S44: Active | T44: 3432 | U44: Tablet | V44: 45-54 | W44: Afternoon | X44: =D44-C44 -> 86 | Y44: {=_xlfn.IFS(E44=7.99,"BASIC",E44=11.99,"STANDARD",E44=15.99,"PREMIUM")} -> BASIC | Z44: =F44/(X44/7) -> 28.651163 | AA44: {=_xlfn.IFS( (F44/(X44/7)) < 5, "Casual", AND((F44/(X44/7)) >= 5, (F44/(X44/7)) < 15), "Regular", (F44/(X44/7)) >= 15, "Power" )} -> Power | AB44: =(F44/(K44+L44)) -> 1.6146789 | AC44: =IF(F44/(K44+L44) < 0.15," Browsers","Viewers") -> Viewers
A45: 1570 | B45: Matthew | C45: 45125 | D45: 45618 | E45: 11.99 | F45: 97 | G45: Romance | H45: 1 | I45: 2 | J45: FALSE | K45: 836 | L45: 122 | M45: UK | N45: Debit Card | O45: Spanish | P45: 65 | Q45: 4.3 | R45: TRUE | S45: Active | T45: 4511 | U45: Smartphone | V45: 18-24 | W45: Morning | X45: =D45-C45 -> 493 | Y45: {=_xlfn.IFS(E45=7.99,"BASIC",E45=11.99,"STANDARD",E45=15.99,"PREMIUM")} -> STANDARD | Z45: =F45/(X45/7) -> 1.3772819 | AA45: {=_xlfn.IFS( (F45/(X45/7)) < 5, "Casual", AND((F45/(X45/7)) >= 5, (F45/(X45/7)) < 15), "Regular", (F45/(X45/7)) >= 15, "Power" )} -> Casual | AB45: =(F45/(K45+L45)) -> 0.10125261 | AC45: =IF(F45/(K45+L45) < 0.15," Browsers","Viewers") -> Browsers
... A121: 3354 | B121: Lisa | C121: 45200 | D121: 45618 | E121: 11.99 | F121: 342 | G121: Comedy | H121: 2 | I121: 2 | J121: FALSE | K121: 503 | L121: 6 | M121: France | N121: PayPal | O121: French | P121: 23 | Q121: 3.2 | R121: TRUE | S121: Active | T121: 3496 | U121: Laptop | V121: 45-54 | W121: Afternoon | X121: =D121-C121 -> 418 | Y121: {=_xlfn.IFS(E121=7.99,"BASIC",E121=11.99,"STANDARD",E121=15.99,"PREMIUM")} -> STANDARD | Z121: =F121/(X121/7) -> 5.7272727 | AA121: {=_xlfn.IFS( (F121/(X121/7)) < 5, "Casual", AND((F121/(X121/7)) >= 5, (F121/(X121/7)) < 15), "Regular", (F121/(X121/7)) >= 15, "Power" )} -> Regular | AB121: =(F121/(K121+L121)) -> 0.6719057 | AC121: =IF(F121/(K121+L121) < 0.15," Browsers","Viewers") -> Viewers
A122: 4668 | B122: Carly | C122: =_xlfn.XLOOKUP(A122,'Data Anomalies -Pls Read It'!A:A,'Data Anomalies -Pls Read It'!D:D,1,0) -> 45635 | D122: =_xlfn.XLOOKUP(A122,'Data Anomalies -Pls Read It'!A:A,'Data Anomalies -Pls Read It'!C:C,1,0) -> 45643 | E122: 11.99 | F122: 396 | G122: Sci-Fi | H122: 5 | I122: 5 | J122: TRUE | K122: 549 | L122: 35 | M122: Canada | N122: PayPal | O122: German | P122: 66 | Q122: 3.6 | R122: TRUE | S122: Active | T122: 4293 | U122: Laptop | V122: 55+ | W122: Morning | X122: =D122-C122 -> 8 | Y122: {=_xlfn.IFS(E122=7.99,"BASIC",E122=11.99,"STANDARD",E122=15.99,"PREMIUM")} -> STANDARD | Z122: =F122/(X122/7) -> 346.5 | AA122: {=_xlfn.IFS( (F122/(X122/7)) < 5, "Casual", AND((F122/(X122/7)) >= 5, (F122/(X122/7)) < 15), "Regular", (F122/(X122/7)) >= 15, "Power" )} -> Power | AB122: =(F122/(K122+L122)) -> 0.67808219 | AC122: =IF(F122/(K122+L122) < 0.15," Browsers","Viewers") -> Viewers | AD122: Correction
A123: 6684 | B123: Dennis | C123: 45552 | D123: 45637 | E123: 11.99 | F123: 491 | G123: Romance | H123: 1 | I123: 6 | J123: TRUE | K123: 434 | L123: 182 | M123: Germany | N123: Cryptocurrency | O123: Spanish | P123: 24 | Q123: 4.1 | R123: FALSE | S123: Active | T123: 1357 | U123: Tablet | V123: 45-54 | W123: Late Night | X123: =D123-C123 -> 85 | Y123: {=_xlfn.IFS(E123=7.99,"BASIC",E123=11.99,"STANDARD",E123=15.99,"PREMIUM")} -> STANDARD | Z123: =F123/(X123/7) -> 40.435294 | AA123: {=_xlfn.IFS( (F123/(X123/7)) < 5, "Casual", AND((F123/(X123/7)) >= 5, (F123/(X123/7)) < 15), "Regular", (F123/(X123/7)) >= 15, "Power" )} -> Power | AB123: =(F123/(K123+L123)) -> 0.79707792 | AC123: =IF(F123/(K123+L123) < 0.15," Browsers","Viewers") -> Viewers
A124: 8058 | B124: Alexandra | C124: 45018 | D124: 45640 | E124: 15.99 | F124: 239 | G124: Sci-Fi | H124: 4 | I124: 6 | J124: FALSE | K124: 832 | L124: 134 | M124: Australia | N124: Cryptocurrency | O124: Spanish | P124: 99 | Q124: 4.6 | R124: TRUE | S124: Active | T124: 3596 | U124: Desktop | V124: 18-24 | W124: Morning | X124: =D124-C124 -> 622 | Y124: {=_xlfn.IFS(E124=7.99,"BASIC",E124=11.99,"STANDARD",E124=15.99,"PREMIUM")} -> PREMIUM | Z124: =F124/(X124/7) -> 2.6897106 | AA124: {=_xlfn.IFS( (F124/(X124/7)) < 5, "Casual", AND((F124/(X124/7)) >= 5, (F124/(X124/7)) < 15), "Regular", (F124/(X124/7)) >= 15, "Power" )} -> Casual | AB124: =(F124/(K124+L124)) -> 0.24741201 | AC124: =IF(F124/(K124+L124) < 0.15," Browsers","Viewers") -> Viewers
A125: 3035 | B125: Michael | C125: 45042 | D125: 45620 | E125: 15.99 | F125: 106 | G125: Romance | H125: 3 | I125: 3 | J125: TRUE | K125: 377 | L125: 31 | M125: Germany | N125: Credit Card | O125: English | P125: 85 | Q125: 3.5 | R125: TRUE | S125: Active | T125: 613 | U125: Desktop | V125: 55+ | W125: Late Night | X125: =D125-C125 -> 578 | Y125: {=_xlfn.IFS(E125=7.99,"BASIC",E125=11.99,"STANDARD",E125=15.99,"PREMIUM")} -> PREMIUM | Z125: =F125/(X125/7) -> 1.283737 | AA125: {=_xlfn.IFS( (F125/(X125/7)) < 5, "Casual", AND((F125/(X125/7)) >= 5, (F125/(X125/7)) < 15), "Regular", (F125/(X125/7)) >= 15, "Power" )} -> Casual | AB125: =(F125/(K125+L125)) -> 0.25980392 | AC125: =IF(F125/(K125+L125) < 0.15," Browsers","Viewers") -> Viewers
A126: 2146 | B126: Ryan | C126: 45484 | D126: 45618 | E126: 11.99 | F126: 388 | G126: Horror | H126: 5 | I126: 4 | J126: TRUE | K126: 380 | L126: 125 | M126: Australia | N126: PayPal | O126: German | P126: 14 | Q126: 3.2 | R126: FALSE | S126: Active | T126: 2381 | U126: Tablet | V126: 25-34 | W126: Afternoon | X126: =D126-C126 -> 134 | Y126: {=_xlfn.IFS(E126=7.99,"BASIC",E126=11.99,"STANDARD",E126=15.99,"PREMIUM")} -> STANDARD | Z126: =F126/(X126/7) -> 20.268657 | AA126: {=_xlfn.IFS( (F126/(X126/7)) < 5, "Casual", AND((F126/(X126/7)) >= 5, (F126/(X126/7)) < 15), "Regular", (F126/(X126/7)) >= 15, "Power" )} -> Power | AB126: =(F126/(K126+L126)) -> 0.76831683 | AC126: =IF(F126/(K126+L126) < 0.15," Browsers","Viewers") -> Viewers
A127: 5761 | B127: Tony | C127: 45311 | D127: 45634 | E127: 15.99 | F127: 452 | G127: Drama | H127: 2 | I127: 5 | J127: FALSE | K127: 315 | L127: 118 | M127: India | N127: Cryptocurrency | O127: Spanish | P127: 28 | Q127: 3 | R127: TRUE | S127: Active | T127: 2159 | U127: Desktop | V127: 45-54 | W127: Morning | X127: =D127-C127 -> 323 | Y127: {=_xlfn.IFS(E127=7.99,"BASIC",E127=11.99,"STANDARD",E127=15.99,"PREMIUM")} -> PREMIUM | Z127: =F127/(X127/7) -> 9.7956656 | AA127: {=_xlfn.IFS( (F127/(X127/7)) < 5, "Casual", AND((F127/(X127/7)) >= 5, (F127/(X127/7)) < 15), "Regular", (F127/(X127/7)) >= 15, "Power" )} -> Regular | AB127: =(F127/(K127+L127)) -> 1.0438799 | AC127: =IF(F127/(K127+L127) < 0.15," Browsers","Viewers") -> Viewers
A128: 5256 | B128: Daniel | C128: 45614 | D128: 45628 | E128: 15.99 | F128: 368 | G128: Sci-Fi | H128: 4 | I128: 4 | J128: TRUE | K128: 968 | L128: 24 | M128: Australia | N128: Debit Card | O128: Mandarin | P128: 30 | Q128: 3 | R128: TRUE | S128: Active | T128: 119 | U128: Tablet | V128: 55+ | W128: Late Night | X128: =D128-C128 -> 14 | Y128: {=_xlfn.IFS(E128=7.99,"BASIC",E128=11.99,"STANDARD",E128=15.99,"PREMIUM")} -> PREMIUM | Z128: =F128/(X128/7) -> 184 | AA128: {=_xlfn.IFS( (F128/(X128/7)) < 5, "Casual", AND((F128/(X128/7)) >= 5, (F128/(X128/7)) < 15), "Regular", (F128/(X128/7)) >= 15, "Power" )} -> Power | AB128: =(F128/(K128+L128)) -> 0.37096774 | AC128: =IF(F128/(K128+L128) < 0.15," Browsers","Viewers") -> Viewers
A129: 5995 | B129: Melissa | C129: 45094 | D129: 45623 | E129: 15.99 | F129: 325 | G129: Action | H129: 2 | I129: 5 | J129: TRUE | K129: 757 | L129: 35 | M129: UK | N129: Credit Card | O129: Mandarin | P129: 81 | Q129: 4.6 | R129: FALSE | S129: Active | T129: 2798 | U129: Smartphone | V129: 25-34 | W129: Late Night | X129: =D129-C129 -> 529 | Y129: {=_xlfn.IFS(E129=7.99,"BASIC",E129=11.99,"STANDARD",E129=15.99,"PREMIUM")} -> PREMIUM | Z129: =F129/(X129/7) -> 4.3005671 | AA129: {=_xlfn.IFS( (F129/(X129/7)) < 5, "Casual", AND((F129/(X129/7)) >= 5, (F129/(X129/7)) < 15), "Regular", (F129/(X129/7)) >= 15, "Power" )} -> Casual | AB129: =(F129/(K129+L129)) -> 0.41035354 | AC129: =IF(F129/(K129+L129) < 0.15," Browsers","Viewers") -> Viewers
A130: 4155 | B130: Jacob | C130: 44992 | D130: 45632 | E130: 11.99 | F130: 42 | G130: Sci-Fi | H130: 4 | I130: 2 | J130: FALSE | K130: 560 | L130: 98 | M130: France | N130: Debit Card | O130: Mandarin | P130: 90 | Q130: 3.8 | R130: FALSE | S130: Active | T130: 496 | U130: Laptop | V130: 18-24 | W130: Afternoon | X130: =D130-C130 -> 640 | Y130: {=_xlfn.IFS(E130=7.99,"BASIC",E130=11.99,"STANDARD",E130=15.99,"PREMIUM")} -> STANDARD | Z130: =F130/(X130/7) -> 0.459375 | AA130: {=_xlfn.IFS( (F130/(X130/7)) < 5, "Casual", AND((F130/(X130/7)) >= 5, (F130/(X130/7)) < 15), "Regular", (F130/(X130/7)) >= 15, "Power" )} -> Casual | AB130: =(F130/(K130+L130)) -> 0.063829787 | AC130: =IF(F130/(K130+L130) < 0.15," Browsers","Viewers") -> Browsers
A131: 1851 | B131: Jennifer | C131: 45202 | D131: 45637 | E131: 11.99 | F131: 344 | G131: Horror | H131: 3 | I131: 1 | J131: FALSE | K131: 456 | L131: 196 | M131: France | N131: Credit Card | O131: Mandarin | P131: 83 | Q131: 5 | R131: FALSE | S131: Active | T131: 3599 | U131: Desktop | V131: 45-54 | W131: Evening | X131: =D131-C131 -> 435 | Y131: {=_xlfn.IFS(E131=7.99,"BASIC",E131=11.99,"STANDARD",E131=15.99,"PREMIUM")} -> STANDARD | Z131: =F131/(X131/7) -> 5.5356322 | AA131: {=_xlfn.IFS( (F131/(X131/7)) < 5, "Casual", AND((F131/(X131/7)) >= 5, (F131/(X131/7)) < 15), "Regular", (F131/(X131/7)) >= 15, "Power" )} -> Regular | AB131: =(F131/(K131+L131)) -> 0.52760736 | AC131: =IF(F131/(K131+L131) < 0.15," Browsers","Viewers") -> Viewers
A132: 8068 | B132: Carolyn | C132: =_xlfn.XLOOKUP(A132,'Data Anomalies -Pls Read It'!A:A,'Data Anomalies -Pls Read It'!D:D,1,0) -> 45619 | D132: =_xlfn.XLOOKUP(A132,'Data Anomalies -Pls Read It'!A:A,'Data Anomalies -Pls Read It'!C:C,1,0) -> 45640 | E132: 15.99 | F132: 77 | G132: Drama | H132: 5 | I132: 3 | J132: FALSE | K132: 780 | L132: 138 | M132: India | N132: Cryptocurrency | O132: French | P132: 66 | Q132: 3.4 | R132: FALSE | S132: Active | T132: 1752 | U132: Tablet | V132: 18-24 | W132: Afternoon | X132: =D132-C132 -> 21 | Y132: {=_xlfn.IFS(E132=7.99,"BASIC",E132=11.99,"STANDARD",E132=15.99,"PREMIUM")} -> PREMIUM | Z132: =F132/(X132/7) -> 25.666667 | AA132: {=_xlfn.IFS( (F132/(X132/7)) < 5, "Casual", AND((F132/(X132/7)) >= 5, (F132/(X132/7)) < 15), "Regular", (F132/(X132/7)) >= 15, "Power" )} -> Power | AB132: =(F132/(K132+L132)) -> 0.083877996 | AC132: =IF(F132/(K132+L132) < 0.15," Browsers","Viewers") -> Browsers | AD132: Correction
A133: 8425 | B133: Patrick | C133: 45610 | D133: 45624 | E133: 7.99 | F133: 237 | G133: Comedy | H133: 5 | I133: 3 | J133: TRUE | K133: 168 | L133: 18 | M133: Australia | N133: Cryptocurrency | O133: Mandarin | P133: 32 | Q133: 3.5 | R133: TRUE | S133: Active | T133: 3633 | U133: Laptop | V133: 25-34 | W133: Evening | X133: =D133-C133 -> 14 | Y133: {=_xlfn.IFS(E133=7.99,"BASIC",E133=11.99,"STANDARD",E133=15.99,"PREMIUM")} -> BASIC | Z133: =F133/(X133/7) -> 118.5 | AA133: {=_xlfn.IFS( (F133/(X133/7)) < 5, "Casual", AND((F133/(X133/7)) >= 5, (F133/(X133/7)) < 15), "Regular", (F133/(X133/7)) >= 15, "Power" )} -> Power | AB133: =(F133/(K133+L133)) -> 1.2741935 | AC133: =IF(F133/(K133+L133) < 0.15," Browsers","Viewers") -> Viewers
A134: 4706 | B134: Sabrina | C134: 44965 | D134: 45632 | E134: 11.99 | F134: 480 | G134: Sci-Fi | H134: 1 | I134: 2 | J134: TRUE | K134: 350 | L134: 122 | M134: France | N134: PayPal | O134: Spanish | P134: 59 | Q134: 4.6 | R134: FALSE | S134: Active | T134: 3568 | U134: Desktop | V134: 35-44 | W134: Late Night | X134: =D134-C134 -> 667 | Y134: {=_xlfn.IFS(E134=7.99,"BASIC",E134=11.99,"STANDARD",E134=15.99,"PREMIUM")} -> STANDARD | Z134: =F134/(X134/7) -> 5.0374813 | AA134: {=_xlfn.IFS( (F134/(X134/7)) < 5, "Casual", AND((F134/(X134/7)) >= 5, (F134/(X134/7)) < 15), "Regular", (F134/(X134/7)) >= 15, "Power" )} -> Regular | AB134: =(F134/(K134+L134)) -> 1.0169492 | AC134: =IF(F134/(K134+L134) < 0.15," Browsers","Viewers") -> Viewers
A135: 7544 | B135: Denise | C135: 45170 | D135: 45621 | E135: 15.99 | F135: 152 | G135: Horror | H135: 1 | I135: 3 | J135: FALSE | K135: 341 | L135: 193 | M135: UK | N135: Credit Card | O135: Mandarin | P135: 95 | Q135: 3.7 | R135: FALSE | S135: Active | T135: 4361 | U135: Smartphone | V135: 45-54 | W135: Afternoon | X135: =D135-C135 -> 451 | Y135: {=_xlfn.IFS(E135=7.99,"BASIC",E135=11.99,"STANDARD",E135=15.99,"PREMIUM")} -> PREMIUM | Z135: =F135/(X135/7) -> 2.3592018 | AA135: {=_xlfn.IFS( (F135/(X135/7)) < 5, "Casual", AND((F135/(X135/7)) >= 5, (F135/(X135/7)) < 15), "Regular", (F135/(X135/7)) >= 15, "Power" )} -> Casual | AB135: =(F135/(K135+L135)) -> 0.28464419 | AC135: =IF(F135/(K135+L135) < 0.15," Browsers","Viewers") -> Viewers
A136: 4029 | B136: Cassandra | C136: 45580 | D136: 45620 | E136: 11.99 | F136: 308 | G136: Drama | H136: 2 | I136: 3 | J136: FALSE | K136: 392 | L136: 151 | M136: Canada | N136: Debit Card | O136: German | P136: 27 | Q136: 4.2 | R136: TRUE | S136: Active | T136: 1176 | U136: Smartphone | V136: 18-24 | W136: Evening | X136: =D136-C136 -> 40 | Y136: {=_xlfn.IFS(E136=7.99,"BASIC",E136=11.99,"STANDARD",E136=15.99,"PREMIUM")} -> STANDARD | Z136: =F136/(X136/7) -> 53.9 | AA136: {=_xlfn.IFS( (F136/(X136/7)) < 5, "Casual", AND((F136/(X136/7)) >= 5, (F136/(X136/7)) < 15), "Regular", (F136/(X136/7)) >= 15, "Power" )} -> Power | AB136: =(F136/(K136+L136)) -> 0.56721915 | AC136: =IF(F136/(K136+L136) < 0.15," Browsers","Viewers") -> Viewers
A137: 6117 | B137: Elizabeth | C137: 45442 | D137: 45623 | E137: 7.99 | F137: 14 | G137: Drama | H137: 5 | I137: 5 | J137: TRUE | K137: 95 | L137: 158 | M137: Australia | N137: Credit Card | O137: Hindi | P137: 49 | Q137: 3.9 | R137: FALSE | S137: Active | T137: 1849 | U137: Tablet | V137: 18-24 | W137: Evening | X137: =D137-C137 -> 181 | Y137: {=_xlfn.IFS(E137=7.99,"BASIC",E137=11.99,"STANDARD",E137=15.99,"PREMIUM")} -> BASIC | Z137: =F137/(X137/7) -> 0.54143646 | AA137: {=_xlfn.IFS( (F137/(X137/7)) < 5, "Casual", AND((F137/(X137/7)) >= 5, (F137/(X137/7)) < 15), "Regular", (F137/(X137/7)) >= 15, "Power" )} -> Casual | AB137: =(F137/(K137+L137)) -> 0.055335968 | AC137: =IF(F137/(K137+L137) < 0.15," Browsers","Viewers") -> Browsers
A138: 1408 | B138: Dustin | C138: 44949 | D138: 45616 | E138: 11.99 | F138: 233 | G138: Drama | H138: 5 | I138: 6 | J138: TRUE | K138: 186 | L138: 129 | M138: India | N138: Debit Card | O138: Hindi | P138: 38 | Q138: 4 | R138: TRUE | S138: Active | T138: 3953 | U138: Laptop | V138: 35-44 | W138: Evening | X138: =D138-C138 -> 667 | Y138: {=_xlfn.IFS(E138=7.99,"BASIC",E138=11.99,"STANDARD",E138=15.99,"PREMIUM")} -> STANDARD | Z138: =F138/(X138/7) -> 2.4452774 | AA138: {=_xlfn.IFS( (F138/(X138/7)) < 5, "Casual", AND((F138/(X138/7)) >= 5, (F138/(X138/7)) < 15), "Regular", (F138/(X138/7)) >= 15, "Power" )} -> Casual | AB138: =(F138/(K138+L138)) -> 0.73968254 | AC138: =IF(F138/(K138+L138) < 0.15," Browsers","Viewers") -> Viewers
A139: 8396 | B139: Mary | C139: 45338 | D139: 45637 | E139: 7.99 | F139: 169 | G139: Documentary | H139: 1 | I139: 5 | J139: FALSE | K139: 543 | L139: 111 | M139: Germany | N139: PayPal | O139: French | P139: 28 | Q139: 3.7 | R139: FALSE | S139: Active | T139: 3277 | U139: Smart TV | V139: 55+ | W139: Evening | X139: =D139-C139 -> 299 | Y139: {=_xlfn.IFS(E139=7.99,"BASIC",E139=11.99,"STANDARD",E139=15.99,"PREMIUM")} -> BASIC | Z139: =F139/(X139/7) -> 3.9565217 | AA139: {=_xlfn.IFS( (F139/(X139/7)) < 5, "Casual", AND((F139/(X139/7)) >= 5, (F139/(X139/7)) < 15), "Regular", (F139/(X139/7)) >= 15, "Power" )} -> Casual | AB139: =(F139/(K139+L139)) -> 0.25840979 | AC139: =IF(F139/(K139+L139) < 0.15," Browsers","Viewers") -> Viewers
A140: 6806 | B140: Crystal | C140: 45278 | D140: 45619 | E140: 7.99 | F140: 358 | G140: Action | H140: 2 | I140: 3 | J140: TRUE | K140: 858 | L140: 65 | M140: Germany | N140: Debit Card | O140: Mandarin | P140: 5 | Q140: 4.6 | R140: TRUE | S140: Active | T140: 1572 | U140: Laptop | V140: 45-54 | W140: Afternoon | X140: =D140-C140 -> 341 | Y140: {=_xlfn.IFS(E140=7.99,"BASIC",E140=11.99,"STANDARD",E140=15.99,"PREMIUM")} -> BASIC | Z140: =F140/(X140/7) -> 7.3489736 | AA140: {=_xlfn.IFS( (F140/(X140/7)) < 5, "Casual", AND((F140/(X140/7)) >= 5, (F140/(X140/7)) < 15), "Regular", (F140/(X140/7)) >= 15, "Power" )} -> Regular | AB140: =(F140/(K140+L140)) -> 0.38786566 | AC140: =IF(F140/(K140+L140) < 0.15," Browsers","Viewers") -> Viewers
A141: 3496 | B141: Gregory | C141: 45254 | D141: 45637 | E141: 11.99 | F141: 404 | G141: Drama | H141: 4 | I141: 6 | J141: FALSE | K141: 906 | L141: 43 | M141: India | N141: PayPal | O141: German | P141: 59 | Q141: 4.9 | R141: TRUE | S141: Active | T141: 2676 | U141: Tablet | V141: 25-34 | W141: Morning | X141: =D141-C141 -> 383 | Y141: {=_xlfn.IFS(E141=7.99,"BASIC",E141=11.99,"STANDARD",E141=15.99,"PREMIUM")} -> STANDARD | Z141: =F141/(X141/7) -> 7.383812 | AA141: {=_xlfn.IFS( (F141/(X141/7)) < 5, "Casual", AND((F141/(X141/7)) >= 5, (F141/(X141/7)) < 15), "Regular", (F141/(X141/7)) >= 15, "Power" )} -> Regular | AB141: =(F141/(K141+L141)) -> 0.42571128 | AC141: =IF(F141/(K141+L141) < 0.15," Browsers","Viewers") -> Viewers
A142: 7840 | B142: Barbara | C142: 45324 | D142: 45637 | E142: 15.99 | F142: 131 | G142: Comedy | H142: 5 | I142: 3 | J142: TRUE | K142: 808 | L142: 48 | M142: UK | N142: PayPal | O142: Hindi | P142: 55 | Q142: 3.3 | R142: TRUE | S142: Active | T142: 3053 | U142: Smart TV | V142: 55+ | W142: Afternoon | X142: =D142-C142 -> 313 | Y142: {=_xlfn.IFS(E142=7.99,"BASIC",E142=11.99,"STANDARD",E142=15.99,"PREMIUM")} -> PREMIUM | Z142: =F142/(X142/7) -> 2.9297125 | AA142: {=_xlfn.IFS( (F142/(X142/7)) < 5, "Casual", AND((F142/(X142/7)) >= 5, (F142/(X142/7)) < 15), "Regular", (F142/(X142/7)) >= 15, "Power" )} -> Casual | AB142: =(F142/(K142+L142)) -> 0.15303738 | AC142: =IF(F142/(K142+L142) < 0.15," Browsers","Viewers") -> Viewers
A143: 2099 | B143: Michael | C143: 45493 | D143: 45619 | E143: 11.99 | F143: 32 | G143: Drama | H143: 1 | I143: 6 | J143: TRUE | K143: 84 | L143: 73 | M143: Germany | N143: Cryptocurrency | O143: Hindi | P143: 59 | Q143: 3.6 | R143: TRUE | S143: Active | T143: 2620 | U143: Desktop | V143: 35-44 | W143: Morning | X143: =D143-C143 -> 126 | Y143: {=_xlfn.IFS(E143=7.99,"BASIC",E143=11.99,"STANDARD",E143=15.99,"PREMIUM")} -> STANDARD | Z143: =F143/(X143/7) -> 1.7777778 | AA143: {=_xlfn.IFS( (F143/(X143/7)) < 5, "Casual", AND((F143/(X143/7)) >= 5, (F143/(X143/7)) < 15), "Regular", (F143/(X143/7)) >= 15, "Power" )} -> Casual | AB143: =(F143/(K143+L143)) -> 0.20382166 | AC143: =IF(F143/(K143+L143) < 0.15," Browsers","Viewers") -> Viewers
A144: 6518 | B144: Kathryn | C144: 45617 | D144: 45633 | E144: 7.99 | F144: 478 | G144: Action | H144: 5 | I144: 3 | J144: TRUE | K144: 780 | L144: 78 | M144: UK | N144: PayPal | O144: Spanish | P144: 66 | Q144: 4 | R144: FALSE | S144: Active | T144: 4068 | U144: Smart TV | V144: 35-44 | W144: Morning | X144: =D144-C144 -> 16 | Y144: {=_xlfn.IFS(E144=7.99,"BASIC",E144=11.99,"STANDARD",E144=15.99,"PREMIUM")} -> BASIC | Z144: =F144/(X144/7) -> 209.125 | AA144: {=_xlfn.IFS( (F144/(X144/7)) < 5, "Casual", AND((F144/(X144/7)) >= 5, (F144/(X144/7)) < 15), "Regular", (F144/(X144/7)) >= 15, "Power" )} -> Power | AB144: =(F144/(K144+L144)) -> 0.55710956 | AC144: =IF(F144/(K144+L144) < 0.15," Browsers","Viewers") -> Viewers
... A149: 6300 | B149: Taylor | C149: 45189 | D149: 45635 | E149: 15.99 | F149: 164 | G149: Action | H149: 3 | I149: 5 | J149: FALSE | K149: 161 | L149: 77 | M149: Australia | N149: Cryptocurrency | O149: German | P149: 97 | Q149: 3.7 | R149: TRUE | S149: Active | T149: 1991 | U149: Laptop | V149: 45-54 | W149: Late Night | X149: =D149-C149 -> 446 | Y149: {=_xlfn.IFS(E149=7.99,"BASIC",E149=11.99,"STANDARD",E149=15.99,"PREMIUM")} -> PREMIUM | Z149: =F149/(X149/7) -> 2.573991 | AA149: {=_xlfn.IFS( (F149/(X149/7)) < 5, "Casual", AND((F149/(X149/7)) >= 5, (F149/(X149/7)) < 15), "Regular", (F149/(X149/7)) >= 15, "Power" )} -> Casual | AB149: =(F149/(K149+L149)) -> 0.68907563 | AC149: =IF(F149/(K149+L149) < 0.15," Browsers","Viewers") -> Viewers
A150: 1003 | B150: Vickie | C150: =_xlfn.XLOOKUP(A150,'Data Anomalies -Pls Read It'!A:A,'Data Anomalies -Pls Read It'!D:D,1,0) -> 45618 | D150: =_xlfn.XLOOKUP(A150,'Data Anomalies -Pls Read It'!A:A,'Data Anomalies -Pls Read It'!C:C,1,0) -> 45638 | E150: 11.99 | F150: 433 | G150: Horror | H150: 5 | I150: 4 | J150: FALSE | K150: 350 | L150: 2 | M150: Germany | N150: Cryptocurrency | O150: Spanish | P150: 41 | Q150: 3.1 | R150: TRUE | S150: Active | T150: 2043 | U150: Smartphone | V150: 35-44 | W150: Late Night | X150: =D150-C150 -> 20 | Y150: {=_xlfn.IFS(E150=7.99,"BASIC",E150=11.99,"STANDARD",E150=15.99,"PREMIUM")} -> STANDARD | Z150: =F150/(X150/7) -> 151.55 | AA150: {=_xlfn.IFS( (F150/(X150/7)) < 5, "Casual", AND((F150/(X150/7)) >= 5, (F150/(X150/7)) < 15), "Regular", (F150/(X150/7)) >= 15, "Power" )} -> Power | AB150: =(F150/(K150+L150)) -> 1.2301136 | AC150: =IF(F150/(K150+L150) < 0.15," Browsers","Viewers") -> Viewers | AD150: Correction
A151: 8238 | B151: Betty | C151: 45303 | D151: 45624 | E151: 7.99 | F151: 460 | G151: Comedy | H151: 3 | I151: 5 | J151: FALSE | K151: 26 | L151: 2 | M151: France | N151: PayPal | O151: German | P151: 39 | Q151: 4.8 | R151: FALSE | S151: Active | T151: 882 | U151: Smartphone | V151: 45-54 | W151: Late Night | X151: =D151-C151 -> 321 | Y151: {=_xlfn.IFS(E151=7.99,"BASIC",E151=11.99,"STANDARD",E151=15.99,"PREMIUM")} -> BASIC | Z151: =F151/(X151/7) -> 10.031153 | AA151: {=_xlfn.IFS( (F151/(X151/7)) < 5, "Casual", AND((F151/(X151/7)) >= 5, (F151/(X151/7)) < 15), "Regular", (F151/(X151/7)) >= 15, "Power" )} -> Regular | AB151: =(F151/(K151+L151)) -> 16.428571 | AC151: =IF(F151/(K151+L151) < 0.15," Browsers","Viewers") -> Viewers
A152: 8261 | B152: James | C152: 44920 | D152: 45630 | E152: 7.99 | F152: 374 | G152: Comedy | H152: 1 | I152: 3 | J152: TRUE | K152: 819 | L152: 18 | M152: Germany | N152: Debit Card | O152: Hindi | P152: 12 | Q152: 3.4 | R152: TRUE | S152: Active | T152: 4243 | U152: Laptop | V152: 25-34 | W152: Morning | X152: =D152-C152 -> 710 | Y152: {=_xlfn.IFS(E152=7.99,"BASIC",E152=11.99,"STANDARD",E152=15.99,"PREMIUM")} -> BASIC | Z152: =F152/(X152/7) -> 3.6873239 | AA152: {=_xlfn.IFS( (F152/(X152/7)) < 5, "Casual", AND((F152/(X152/7)) >= 5, (F152/(X152/7)) < 15), "Regular", (F152/(X152/7)) >= 15, "Power" )} -> Casual | AB152: =(F152/(K152+L152)) -> 0.44683393 | AC152: =IF(F152/(K152+L152) < 0.15," Browsers","Viewers") -> Viewers
A153: 7729 | B153: Brittany | C153: 44977 | D153: 45637 | E153: 11.99 | F153: 147 | G153: Romance | H153: 5 | I153: 4 | J153: FALSE | K153: 27 | L153: 175 | M153: Germany | N153: PayPal | O153: Hindi | P153: 78 | Q153: 4 | R153: TRUE | S153: Active | T153: 2218 | U153: Desktop | V153: 45-54 | W153: Afternoon | X153: =D153-C153 -> 660 | Y153: {=_xlfn.IFS(E153=7.99,"BASIC",E153=11.99,"STANDARD",E153=15.99,"PREMIUM")} -> STANDARD | Z153: =F153/(X153/7) -> 1.5590909 | AA153: {=_xlfn.IFS( (F153/(X153/7)) < 5, "Casual", AND((F153/(X153/7)) >= 5, (F153/(X153/7)) < 15), "Regular", (F153/(X153/7)) >= 15, "Power" )} -> Casual | AB153: =(F153/(K153+L153)) -> 0.72772277 | AC153: =IF(F153/(K153+L153) < 0.15," Browsers","Viewers") -> Viewers
A154: 8616 | B154: John | C154: 45627 | D154: 45630 | E154: 11.99 | F154: 129 | G154: Horror | H154: 4 | I154: 6 | J154: FALSE | K154: 543 | L154: 126 | M154: UK | N154: Debit Card | O154: Mandarin | P154: 95 | Q154: 3.4 | R154: TRUE | S154: Active | T154: 97 | U154: Smartphone | V154: 35-44 | W154: Late Night | X154: =D154-C154 -> 3 | Y154: {=_xlfn.IFS(E154=7.99,"BASIC",E154=11.99,"STANDARD",E154=15.99,"PREMIUM")} -> STANDARD | Z154: =F154/(X154/7) -> 301 | AA154: {=_xlfn.IFS( (F154/(X154/7)) < 5, "Casual", AND((F154/(X154/7)) >= 5, (F154/(X154/7)) < 15), "Regular", (F154/(X154/7)) >= 15, "Power" )} -> Power | AB154: =(F154/(K154+L154)) -> 0.19282511 | AC154: =IF(F154/(K154+L154) < 0.15," Browsers","Viewers") -> Viewers
A155: 9734 | B155: Destiny | C155: 45620 | D155: 45640 | E155: 15.99 | F155: 217 | G155: Action | H155: 2 | I155: 2 | J155: TRUE | K155: 872 | L155: 8 | M155: Canada | N155: Cryptocurrency | O155: French | P155: 51 | Q155: 3.6 | R155: TRUE | S155: Active | T155: 4928 | U155: Laptop | V155: 35-44 | W155: Late Night | X155: =D155-C155 -> 20 | Y155: {=_xlfn.IFS(E155=7.99,"BASIC",E155=11.99,"STANDARD",E155=15.99,"PREMIUM")} -> PREMIUM | Z155: =F155/(X155/7) -> 75.95 | AA155: {=_xlfn.IFS( (F155/(X155/7)) < 5, "Casual", AND((F155/(X155/7)) >= 5, (F155/(X155/7)) < 15), "Regular", (F155/(X155/7)) >= 15, "Power" )} -> Power | AB155: =(F155/(K155+L155)) -> 0.24659091 | AC155: =IF(F155/(K155+L155) < 0.15," Browsers","Viewers") -> Viewers
A156: 2086 | B156: Amanda | C156: 45058 | D156: 45615 | E156: 7.99 | F156: 426 | G156: Drama | H156: 4 | I156: 1 | J156: FALSE | K156: 606 | L156: 135 | M156: USA | N156: PayPal | O156: German | P156: 50 | Q156: 3.8 | R156: TRUE | S156: Active | T156: 1982 | U156: Desktop | V156: 55+ | W156: Late Night | X156: =D156-C156 -> 557 | Y156: {=_xlfn.IFS(E156=7.99,"BASIC",E156=11.99,"STANDARD",E156=15.99,"PREMIUM")} -> BASIC | Z156: =F156/(X156/7) -> 5.3536804 | AA156: {=_xlfn.IFS( (F156/(X156/7)) < 5, "Casual", AND((F156/(X156/7)) >= 5, (F156/(X156/7)) < 15), "Regular", (F156/(X156/7)) >= 15, "Power" )} -> Regular | AB156: =(F156/(K156+L156)) -> 0.57489879 | AC156: =IF(F156/(K156+L156) < 0.15," Browsers","Viewers") -> Viewers
A157: 8721 | B157: Stephen | C157: 44980 | D157: 45627 | E157: 15.99 | F157: 81 | G157: Drama | H157: 3 | I157: 5 | J157: FALSE | K157: 394 | L157: 168 | M157: Canada | N157: Cryptocurrency | O157: Mandarin | P157: 21 | Q157: 4.7 | R157: TRUE | S157: Active | T157: 510 | U157: Smart TV | V157: 18-24 | W157: Late Night | X157: =D157-C157 -> 647 | Y157: {=_xlfn.IFS(E157=7.99,"BASIC",E157=11.99,"STANDARD",E157=15.99,"PREMIUM")} -> PREMIUM | Z157: =F157/(X157/7) -> 0.8763524 | AA157: {=_xlfn.IFS( (F157/(X157/7)) < 5, "Casual", AND((F157/(X157/7)) >= 5, (F157/(X157/7)) < 15), "Regular", (F157/(X157/7)) >= 15, "Power" )} -> Casual | AB157: =(F157/(K157+L157)) -> 0.14412811 | AC157: =IF(F157/(K157+L157) < 0.15," Browsers","Viewers") -> Browsers
A158: 1075 | B158: Dawn | C158: 45051 | D158: 45624 | E158: 7.99 | F158: 296 | G158: Romance | H158: 3 | I158: 2 | J158: TRUE | K158: 411 | L158: 96 | M158: USA | N158: Cryptocurrency | O158: English | P158: 1 | Q158: 3.1 | R158: FALSE | S158: Active | T158: 2508 | U158: Tablet | V158: 18-24 | W158: Evening | X158: =D158-C158 -> 573 | Y158: {=_xlfn.IFS(E158=7.99,"BASIC",E158=11.99,"STANDARD",E158=15.99,"PREMIUM")} -> BASIC | Z158: =F158/(X158/7) -> 3.6160558 | AA158: {=_xlfn.IFS( (F158/(X158/7)) < 5, "Casual", AND((F158/(X158/7)) >= 5, (F158/(X158/7)) < 15), "Regular", (F158/(X158/7)) >= 15, "Power" )} -> Casual | AB158: =(F158/(K158+L158)) -> 0.58382643 | AC158: =IF(F158/(K158+L158) < 0.15," Browsers","Viewers") -> Viewers
A159: 2690 | B159: Jonathan | C159: 45174 | D159: 45625 | E159: 15.99 | F159: 466 | G159: Sci-Fi | H159: 3 | I159: 2 | J159: FALSE | K159: 977 | L159: 94 | M159: France | N159: Cryptocurrency | O159: Mandarin | P159: 67 | Q159: 3.6 | R159: TRUE | S159: Active | T159: 4004 | U159: Smartphone | V159: 35-44 | W159: Afternoon | X159: =D159-C159 -> 451 | Y159: {=_xlfn.IFS(E159=7.99,"BASIC",E159=11.99,"STANDARD",E159=15.99,"PREMIUM")} -> PREMIUM | Z159: =F159/(X159/7) -> 7.232816 | AA159: {=_xlfn.IFS( (F159/(X159/7)) < 5, "Casual", AND((F159/(X159/7)) >= 5, (F159/(X159/7)) < 15), "Regular", (F159/(X159/7)) >= 15, "Power" )} -> Regular | AB159: =(F159/(K159+L159)) -> 0.43510738 | AC159: =IF(F159/(K159+L159) < 0.15," Browsers","Viewers") -> Viewers
A160: 7654 | B160: Amy | C160: 45279 | D160: 45623 | E160: 11.99 | F160: 424 | G160: Horror | H160: 5 | I160: 2 | J160: FALSE | K160: 406 | L160: 150 | M160: Canada | N160: Debit Card | O160: Spanish | P160: 50 | Q160: 3.5 | R160: FALSE | S160: Active | T160: 494 | U160: Smart TV | V160: 25-34 | W160: Late Night | X160: =D160-C160 -> 344 | Y160: {=_xlfn.IFS(E160=7.99,"BASIC",E160=11.99,"STANDARD",E160=15.99,"PREMIUM")} -> STANDARD | Z160: =F160/(X160/7) -> 8.627907 | AA160: {=_xlfn.IFS( (F160/(X160/7)) < 5, "Casual", AND((F160/(X160/7)) >= 5, (F160/(X160/7)) < 15), "Regular", (F160/(X160/7)) >= 15, "Power" )} -> Regular | AB160: =(F160/(K160+L160)) -> 0.76258993 | AC160: =IF(F160/(K160+L160) < 0.15," Browsers","Viewers") -> Viewers
A161: 7577 | B161: Paul | C161: 45582 | D161: 45629 | E161: 15.99 | F161: 233 | G161: Sci-Fi | H161: 2 | I161: 5 | J161: TRUE | K161: 781 | L161: 23 | M161: France | N161: Credit Card | O161: Hindi | P161: 89 | Q161: 3.3 | R161: FALSE | S161: Active | T161: 460 | U161: Tablet | V161: 45-54 | W161: Morning | X161: =D161-C161 -> 47 | Y161: {=_xlfn.IFS(E161=7.99,"BASIC",E161=11.99,"STANDARD",E161=15.99,"PREMIUM")} -> PREMIUM | Z161: =F161/(X161/7) -> 34.702128 | AA161: {=_xlfn.IFS( (F161/(X161/7)) < 5, "Casual", AND((F161/(X161/7)) >= 5, (F161/(X161/7)) < 15), "Regular", (F161/(X161/7)) >= 15, "Power" )} -> Power | AB161: =(F161/(K161+L161)) -> 0.289801 | AC161: =IF(F161/(K161+L161) < 0.15," Browsers","Viewers") -> Viewers
A162: 9814 | B162: Kenneth | C162: 45515 | D162: 45623 | E162: 11.99 | F162: 413 | G162: Comedy | H162: 1 | I162: 6 | J162: TRUE | K162: 330 | L162: 63 | M162: USA | N162: PayPal | O162: French | P162: 50 | Q162: 4.1 | R162: TRUE | S162: Active | T162: 1416 | U162: Smart TV | V162: 45-54 | W162: Late Night | X162: =D162-C162 -> 108 | Y162: {=_xlfn.IFS(E162=7.99,"BASIC",E162=11.99,"STANDARD",E162=15.99,"PREMIUM")} -> STANDARD | Z162: =F162/(X162/7) -> 26.768519 | AA162: {=_xlfn.IFS( (F162/(X162/7)) < 5, "Casual", AND((F162/(X162/7)) >= 5, (F162/(X162/7)) < 15), "Regular", (F162/(X162/7)) >= 15, "Power" )} -> Power | AB162: =(F162/(K162+L162)) -> 1.0508906 | AC162: =IF(F162/(K162+L162) < 0.15," Browsers","Viewers") -> Viewers
... A172: 9163 | B172: Martin | C172: 45020 | D172: 45623 | E172: 11.99 | F172: 203 | G172: Sci-Fi | H172: 4 | I172: 4 | J172: TRUE | K172: 874 | L172: 67 | M172: India | N172: Debit Card | O172: French | P172: 94 | Q172: 3.9 | R172: TRUE | S172: Active | T172: 4450 | U172: Smartphone | V172: 35-44 | W172: Afternoon | X172: =D172-C172 -> 603 | Y172: {=_xlfn.IFS(E172=7.99,"BASIC",E172=11.99,"STANDARD",E172=15.99,"PREMIUM")} -> STANDARD | Z172: =F172/(X172/7) -> 2.3565506 | AA172: {=_xlfn.IFS( (F172/(X172/7)) < 5, "Casual", AND((F172/(X172/7)) >= 5, (F172/(X172/7)) < 15), "Regular", (F172/(X172/7)) >= 15, "Power" )} -> Casual | AB172: =(F172/(K172+L172)) -> 0.21572795 | AC172: =IF(F172/(K172+L172) < 0.15," Browsers","Viewers") -> Viewers
A173: 1284 | B173: Michael | C173: =_xlfn.XLOOKUP(A173,'Data Anomalies -Pls Read It'!A:A,'Data Anomalies -Pls Read It'!D:D,1,0) -> 45627 | D173: =_xlfn.XLOOKUP(A173,'Data Anomalies -Pls Read It'!A:A,'Data Anomalies -Pls Read It'!C:C,1,0) -> 45630 | E173: 7.99 | F173: 405 | G173: Comedy | H173: 4 | I173: 3 | J173: TRUE | K173: 695 | L173: 85 | M173: Australia | N173: Credit Card | O173: French | P173: 42 | Q173: 3.7 | R173: FALSE | S173: Active | T173: 2395 | U173: Laptop | V173: 25-34 | W173: Morning | X173: =D173-C173 -> 3 | Y173: {=_xlfn.IFS(E173=7.99,"BASIC",E173=11.99,"STANDARD",E173=15.99,"PREMIUM")} -> BASIC | Z173: =F173/(X173/7) -> 945 | AA173: {=_xlfn.IFS( (F173/(X173/7)) < 5, "Casual", AND((F173/(X173/7)) >= 5, (F173/(X173/7)) < 15), "Regular", (F173/(X173/7)) >= 15, "Power" )} -> Power | AB173: =(F173/(K173+L173)) -> 0.51923077 | AC173: =IF(F173/(K173+L173) < 0.15," Browsers","Viewers") -> Viewers | AD173: Correction
A174: 8774 | B174: Hunter | C174: 45233 | D174: 45634 | E174: 15.99 | F174: 496 | G174: Comedy | H174: 5 | I174: 6 | J174: FALSE | K174: 803 | L174: 130 | M174: USA | N174: Cryptocurrency | O174: French | P174: 4 | Q174: 4.8 | R174: FALSE | S174: Active | T174: 4504 | U174: Smart TV | V174: 45-54 | W174: Morning | X174: =D174-C174 -> 401 | Y174: {=_xlfn.IFS(E174=7.99,"BASIC",E174=11.99,"STANDARD",E174=15.99,"PREMIUM")} -> PREMIUM | Z174: =F174/(X174/7) -> 8.6583541 | AA174: {=_xlfn.IFS( (F174/(X174/7)) < 5, "Casual", AND((F174/(X174/7)) >= 5, (F174/(X174/7)) < 15), "Regular", (F174/(X174/7)) >= 15, "Power" )} -> Regular | AB174: =(F174/(K174+L174)) -> 0.53161844 | AC174: =IF(F174/(K174+L174) < 0.15," Browsers","Viewers") -> Viewers
A175: 3866 | B175: Catherine | C175: 45323 | D175: 45624 | E175: 15.99 | F175: 328 | G175: Sci-Fi | H175: 2 | I175: 2 | J175: FALSE | K175: 268 | L175: 50 | M175: Germany | N175: Debit Card | O175: Mandarin | P175: 3 | Q175: 4.4 | R175: TRUE | S175: Active | T175: 3015 | U175: Laptop | V175: 18-24 | W175: Evening | X175: =D175-C175 -> 301 | Y175: {=_xlfn.IFS(E175=7.99,"BASIC",E175=11.99,"STANDARD",E175=15.99,"PREMIUM")} -> PREMIUM | Z175: =F175/(X175/7) -> 7.627907 | AA175: {=_xlfn.IFS( (F175/(X175/7)) < 5, "Casual", AND((F175/(X175/7)) >= 5, (F175/(X175/7)) < 15), "Regular", (F175/(X175/7)) >= 15, "Power" )} -> Regular | AB175: =(F175/(K175+L175)) -> 1.0314465 | AC175: =IF(F175/(K175+L175) < 0.15," Browsers","Viewers") -> Viewers
A176: 4477 | B176: Christopher | C176: 45410 | D176: 45619 | E176: 7.99 | F176: 85 | G176: Drama | H176: 5 | I176: 1 | J176: FALSE | K176: 429 | L176: 52 | M176: UK | N176: PayPal | O176: German | P176: 16 | Q176: 3.8 | R176: FALSE | S176: Active | T176: 4971 | U176: Smartphone | V176: 45-54 | W176: Evening | X176: =D176-C176 -> 209 | Y176: {=_xlfn.IFS(E176=7.99,"BASIC",E176=11.99,"STANDARD",E176=15.99,"PREMIUM")} -> BASIC | Z176: =F176/(X176/7) -> 2.84689 | AA176: {=_xlfn.IFS( (F176/(X176/7)) < 5, "Casual", AND((F176/(X176/7)) >= 5, (F176/(X176/7)) < 15), "Regular", (F176/(X176/7)) >= 15, "Power" )} -> Casual | AB176: =(F176/(K176+L176)) -> 0.17671518 | AC176: =IF(F176/(K176+L176) < 0.15," Browsers","Viewers") -> Viewers
A177: 4829 | B177: Jeff | C177: 45556 | D177: 45643 | E177: 11.99 | F177: 386 | G177: Sci-Fi | H177: 3 | I177: 4 | J177: FALSE | K177: 62 | L177: 50 | M177: Germany | N177: Credit Card | O177: Hindi | P177: 44 | Q177: 4.7 | R177: FALSE | S177: Active | T177: 2377 | U177: Smartphone | V177: 35-44 | W177: Morning | X177: =D177-C177 -> 87 | Y177: {=_xlfn.IFS(E177=7.99,"BASIC",E177=11.99,"STANDARD",E177=15.99,"PREMIUM")} -> STANDARD | Z177: =F177/(X177/7) -> 31.057471 | AA177: {=_xlfn.IFS( (F177/(X177/7)) < 5, "Casual", AND((F177/(X177/7)) >= 5, (F177/(X177/7)) < 15), "Regular", (F177/(X177/7)) >= 15, "Power" )} -> Power | AB177: =(F177/(K177+L177)) -> 3.4464286 | AC177: =IF(F177/(K177+L177) < 0.15," Browsers","Viewers") -> Viewers
A178: 1257 | B178: Daniel | C178: 44965 | D178: 45634 | E178: 7.99 | F178: 245 | G178: Action | H178: 3 | I178: 4 | J178: FALSE | K178: 831 | L178: 15 | M178: Canada | N178: PayPal | O178: German | P178: 64 | Q178: 4.9 | R178: FALSE | S178: Active | T178: 212 | U178: Tablet | V178: 45-54 | W178: Afternoon | X178: =D178-C178 -> 669 | Y178: {=_xlfn.IFS(E178=7.99,"BASIC",E178=11.99,"STANDARD",E178=15.99,"PREMIUM")} -> BASIC | Z178: =F178/(X178/7) -> 2.5635277 | AA178: {=_xlfn.IFS( (F178/(X178/7)) < 5, "Casual", AND((F178/(X178/7)) >= 5, (F178/(X178/7)) < 15), "Regular", (F178/(X178/7)) >= 15, "Power" )} -> Casual | AB178: =(F178/(K178+L178)) -> 0.28959811 | AC178: =IF(F178/(K178+L178) < 0.15," Browsers","Viewers") -> Viewers
A179: 1897 | B179: Cathy | C179: 45004 | D179: 45642 | E179: 11.99 | F179: 97 | G179: Horror | H179: 5 | I179: 5 | J179: TRUE | K179: 737 | L179: 85 | M179: India | N179: PayPal | O179: French | P179: 80 | Q179: 3.6 | R179: TRUE | S179: Active | T179: 188 | U179: Smartphone | V179: 55+ | W179: Afternoon | X179: =D179-C179 -> 638 | Y179: {=_xlfn.IFS(E179=7.99,"BASIC",E179=11.99,"STANDARD",E179=15.99,"PREMIUM")} -> STANDARD | Z179: =F179/(X179/7) -> 1.0642633 | AA179: {=_xlfn.IFS( (F179/(X179/7)) < 5, "Casual", AND((F179/(X179/7)) >= 5, (F179/(X179/7)) < 15), "Regular", (F179/(X179/7)) >= 15, "Power" )} -> Casual | AB179: =(F179/(K179+L179)) -> 0.11800487 | AC179: =IF(F179/(K179+L179) < 0.15," Browsers","Viewers") -> Browsers
A180: 3603 | B180: Sylvia | C180: 45020 | D180: 45616 | E180: 7.99 | F180: 216 | G180: Documentary | H180: 4 | I180: 3 | J180: TRUE | K180: 923 | L180: 143 | M180: USA | N180: Credit Card | O180: Mandarin | P180: 20 | Q180: 3.4 | R180: FALSE | S180: Active | T180: 4435 | U180: Desktop | V180: 55+ | W180: Late Night | X180: =D180-C180 -> 596 | Y180: {=_xlfn.IFS(E180=7.99,"BASIC",E180=11.99,"STANDARD",E180=15.99,"PREMIUM")} -> BASIC | Z180: =F180/(X180/7) -> 2.5369128 | AA180: {=_xlfn.IFS( (F180/(X180/7)) < 5, "Casual", AND((F180/(X180/7)) >= 5, (F180/(X180/7)) < 15), "Regular", (F180/(X180/7)) >= 15, "Power" )} -> Casual | AB180: =(F180/(K180+L180)) -> 0.20262664 | AC180: =IF(F180/(K180+L180) < 0.15," Browsers","Viewers") -> Viewers
A181: 9256 | B181: Daniel | C181: 44964 | D181: 45618 | E181: 7.99 | F181: 331 | G181: Romance | H181: 5 | I181: 1 | J181: FALSE | K181: 85 | L181: 117 | M181: France | N181: Credit Card | O181: French | P181: 21 | Q181: 4.8 | R181: TRUE | S181: Active | T181: 1454 | U181: Smart TV | V181: 25-34 | W181: Afternoon | X181: =D181-C181 -> 654 | Y181: {=_xlfn.IFS(E181=7.99,"BASIC",E181=11.99,"STANDARD",E181=15.99,"PREMIUM")} -> BASIC | Z181: =F181/(X181/7) -> 3.5428135 | AA181: {=_xlfn.IFS( (F181/(X181/7)) < 5, "Casual", AND((F181/(X181/7)) >= 5, (F181/(X181/7)) < 15), "Regular", (F181/(X181/7)) >= 15, "Power" )} -> Casual | AB181: =(F181/(K181+L181)) -> 1.6386139 | AC181: =IF(F181/(K181+L181) < 0.15," Browsers","Viewers") -> Viewers
A182: 9469 | B182: William | C182: 45087 | D182: 45621 | E182: 11.99 | F182: 451 | G182: Sci-Fi | H182: 2 | I182: 3 | J182: FALSE | K182: 59 | L182: 38 | M182: Germany | N182: Credit Card | O182: German | P182: 94 | Q182: 3 | R182: TRUE | S182: Active | T182: 2841 | U182: Laptop | V182: 45-54 | W182: Evening | X182: =D182-C182 -> 534 | Y182: {=_xlfn.IFS(E182=7.99,"BASIC",E182=11.99,"STANDARD",E182=15.99,"PREMIUM")} -> STANDARD | Z182: =F182/(X182/7) -> 5.911985 | AA182: {=_xlfn.IFS( (F182/(X182/7)) < 5, "Casual", AND((F182/(X182/7)) >= 5, (F182/(X182/7)) < 15), "Regular", (F182/(X182/7)) >= 15, "Power" )} -> Regular | AB182: =(F182/(K182+L182)) -> 4.6494845 | AC182: =IF(F182/(K182+L182) < 0.15," Browsers","Viewers") -> Viewers
A183: 7136 | B183: Jessica | C183: 45431 | D183: 45640 | E183: 7.99 | F183: 326 | G183: Action | H183: 5 | I183: 1 | J183: FALSE | K183: 590 | L183: 105 | M183: France | N183: PayPal | O183: Hindi | P183: 56 | Q183: 3.3 | R183: FALSE | S183: Active | T183: 1626 | U183: Smartphone | V183: 25-34 | W183: Afternoon | X183: =D183-C183 -> 209 | Y183: {=_xlfn.IFS(E183=7.99,"BASIC",E183=11.99,"STANDARD",E183=15.99,"PREMIUM")} -> BASIC | Z183: =F183/(X183/7) -> 10.91866 | AA183: {=_xlfn.IFS( (F183/(X183/7)) < 5, "Casual", AND((F183/(X183/7)) >= 5, (F183/(X183/7)) < 15), "Regular", (F183/(X183/7)) >= 15, "Power" )} -> Regular | AB183: =(F183/(K183+L183)) -> 0.46906475 | AC183: =IF(F183/(K183+L183) < 0.15," Browsers","Viewers") -> Viewers
A184: 2321 | B184: Joseph | C184: 45342 | D184: 45640 | E184: 15.99 | F184: 358 | G184: Drama | H184: 3 | I184: 1 | J184: FALSE | K184: 348 | L184: 49 | M184: France | N184: Debit Card | O184: Hindi | P184: 14 | Q184: 4.2 | R184: FALSE | S184: Active | T184: 111 | U184: Desktop | V184: 35-44 | W184: Morning | X184: =D184-C184 -> 298 | Y184: {=_xlfn.IFS(E184=7.99,"BASIC",E184=11.99,"STANDARD",E184=15.99,"PREMIUM")} -> PREMIUM | Z184: =F184/(X184/7) -> 8.409396 | AA184: {=_xlfn.IFS( (F184/(X184/7)) < 5, "Casual", AND((F184/(X184/7)) >= 5, (F184/(X184/7)) < 15), "Regular", (F184/(X184/7)) >= 15, "Power" )} -> Regular | AB184: =(F184/(K184+L184)) -> 0.90176322 | AC184: =IF(F184/(K184+L184) < 0.15," Browsers","Viewers") -> Viewers
A185: 4243 | B185: Christopher | C185: 44998 | D185: 45625 | E185: 15.99 | F185: 91 | G185: Action | H185: 2 | I185: 1 | J185: TRUE | K185: 561 | L185: 153 | M185: Canada | N185: Cryptocurrency | O185: English | P185: 7 | Q185: 4.1 | R185: FALSE | S185: Active | T185: 450 | U185: Tablet | V185: 55+ | W185: Morning | X185: =D185-C185 -> 627 | Y185: {=_xlfn.IFS(E185=7.99,"BASIC",E185=11.99,"STANDARD",E185=15.99,"PREMIUM")} -> PREMIUM | Z185: =F185/(X185/7) -> 1.015949 | AA185: {=_xlfn.IFS( (F185/(X185/7)) < 5, "Casual", AND((F185/(X185/7)) >= 5, (F185/(X185/7)) < 15), "Regular", (F185/(X185/7)) >= 15, "Power" )} -> Casual | AB185: =(F185/(K185+L185)) -> 0.12745098 | AC185: =IF(F185/(K185+L185) < 0.15," Browsers","Viewers") -> Browsers
... A193: 4808 | B193: Amanda | C193: 45377 | D193: 45623 | E193: 7.99 | F193: 371 | G193: Romance | H193: 1 | I193: 1 | J193: TRUE | K193: 819 | L193: 71 | M193: Canada | N193: PayPal | O193: Spanish | P193: 36 | Q193: 4.1 | R193: TRUE | S193: Active | T193: 2328 | U193: Desktop | V193: 45-54 | W193: Late Night | X193: =D193-C193 -> 246 | Y193: {=_xlfn.IFS(E193=7.99,"BASIC",E193=11.99,"STANDARD",E193=15.99,"PREMIUM")} -> BASIC | Z193: =F193/(X193/7) -> 10.556911 | AA193: {=_xlfn.IFS( (F193/(X193/7)) < 5, "Casual", AND((F193/(X193/7)) >= 5, (F193/(X193/7)) < 15), "Regular", (F193/(X193/7)) >= 15, "Power" )} -> Regular | AB193: =(F193/(K193+L193)) -> 0.41685393 | AC193: =IF(F193/(K193+L193) < 0.15," Browsers","Viewers") -> Viewers
A194: 3633 | B194: Randy | C194: =_xlfn.XLOOKUP(A194,'Data Anomalies -Pls Read It'!A:A,'Data Anomalies -Pls Read It'!D:D,1,0) -> 45636 | D194: =_xlfn.XLOOKUP(A194,'Data Anomalies -Pls Read It'!A:A,'Data Anomalies -Pls Read It'!C:C,1,0) -> 45644 | E194: 7.99 | F194: 176 | G194: Action | H194: 5 | I194: 1 | J194: TRUE | K194: 936 | L194: 11 | M194: France | N194: Cryptocurrency | O194: English | P194: 42 | Q194: 3.2 | R194: FALSE | S194: Active | T194: 4414 | U194: Smartphone | V194: 35-44 | W194: Late Night | X194: =D194-C194 -> 8 | Y194: {=_xlfn.IFS(E194=7.99,"BASIC",E194=11.99,"STANDARD",E194=15.99,"PREMIUM")} -> BASIC | Z194: =F194/(X194/7) -> 154 | AA194: {=_xlfn.IFS( (F194/(X194/7)) < 5, "Casual", AND((F194/(X194/7)) >= 5, (F194/(X194/7)) < 15), "Regular", (F194/(X194/7)) >= 15, "Power" )} -> Power | AB194: =(F194/(K194+L194)) -> 0.18585005 | AC194: =IF(F194/(K194+L194) < 0.15," Browsers","Viewers") -> Viewers | AD194: Correction
A195: 4979 | B195: Tony | C195: 45612 | D195: 45620 | E195: 15.99 | F195: 312 | G195: Drama | H195: 4 | I195: 4 | J195: FALSE | K195: 321 | L195: 19 | M195: Australia | N195: PayPal | O195: Spanish | P195: 18 | Q195: 4.3 | R195: TRUE | S195: Active | T195: 3980 | U195: Laptop | V195: 25-34 | W195: Evening | X195: =D195-C195 -> 8 | Y195: {=_xlfn.IFS(E195=7.99,"BASIC",E195=11.99,"STANDARD",E195=15.99,"PREMIUM")} -> PREMIUM | Z195: =F195/(X195/7) -> 273 | AA195: {=_xlfn.IFS( (F195/(X195/7)) < 5, "Casual", AND((F195/(X195/7)) >= 5, (F195/(X195/7)) < 15), "Regular", (F195/(X195/7)) >= 15, "Power" )} -> Power | AB195: =(F195/(K195+L195)) -> 0.91764706 | AC195: =IF(F195/(K195+L195) < 0.15," Browsers","Viewers") -> Viewers
A196: 2214 | B196: Michelle | C196: 45586 | D196: 45620 | E196: 7.99 | F196: 375 | G196: Romance | H196: 1 | I196: 1 | J196: TRUE | K196: 244 | L196: 106 | M196: India | N196: PayPal | O196: French | P196: 16 | Q196: 3.9 | R196: TRUE | S196: Active | T196: 3596 | U196: Smartphone | V196: 25-34 | W196: Late Night | X196: =D196-C196 -> 34 | Y196: {=_xlfn.IFS(E196=7.99,"BASIC",E196=11.99,"STANDARD",E196=15.99,"PREMIUM")} -> BASIC | Z196: =F196/(X196/7) -> 77.205882 | AA196: {=_xlfn.IFS( (F196/(X196/7)) < 5, "Casual", AND((F196/(X196/7)) >= 5, (F196/(X196/7)) < 15), "Regular", (F196/(X196/7)) >= 15, "Power" )} -> Power | AB196: =(F196/(K196+L196)) -> 1.0714286 | AC196: =IF(F196/(K196+L196) < 0.15," Browsers","Viewers") -> Viewers
A197: 6606 | B197: Danielle | C197: 45317 | D197: 45625 | E197: 15.99 | F197: 134 | G197: Sci-Fi | H197: 3 | I197: 5 | J197: TRUE | K197: 826 | L197: 160 | M197: France | N197: Cryptocurrency | O197: English | P197: 96 | Q197: 3.6 | R197: TRUE | S197: Active | T197: 1150 | U197: Smartphone | V197: 25-34 | W197: Late Night | X197: =D197-C197 -> 308 | Y197: {=_xlfn.IFS(E197=7.99,"BASIC",E197=11.99,"STANDARD",E197=15.99,"PREMIUM")} -> PREMIUM | Z197: =F197/(X197/7) -> 3.0454545 | AA197: {=_xlfn.IFS( (F197/(X197/7)) < 5, "Casual", AND((F197/(X197/7)) >= 5, (F197/(X197/7)) < 15), "Regular", (F197/(X197/7)) >= 15, "Power" )} -> Casual | AB197: =(F197/(K197+L197)) -> 0.13590264 | AC197: =IF(F197/(K197+L197) < 0.15," Browsers","Viewers") -> Browsers
A198: 4246 | B198: Jacob | C198: 45193 | D198: 45641 | E198: 7.99 | F198: 91 | G198: Drama | H198: 5 | I198: 1 | J198: FALSE | K198: 159 | L198: 14 | M198: UK | N198: PayPal | O198: Spanish | P198: 85 | Q198: 4.4 | R198: FALSE | S198: Active | T198: 1858 | U198: Smart TV | V198: 35-44 | W198: Late Night | X198: =D198-C198 -> 448 | Y198: {=_xlfn.IFS(E198=7.99,"BASIC",E198=11.99,"STANDARD",E198=15.99,"PREMIUM")} -> BASIC | Z198: =F198/(X198/7) -> 1.421875 | AA198: {=_xlfn.IFS( (F198/(X198/7)) < 5, "Casual", AND((F198/(X198/7)) >= 5, (F198/(X198/7)) < 15), "Regular", (F198/(X198/7)) >= 15, "Power" )} -> Casual | AB198: =(F198/(K198+L198)) -> 0.52601156 | AC198: =IF(F198/(K198+L198) < 0.15," Browsers","Viewers") -> Viewers
A199: 2836 | B199: Samantha | C199: 45329 | D199: 45643 | E199: 7.99 | F199: 359 | G199: Horror | H199: 2 | I199: 6 | J199: FALSE | K199: 305 | L199: 81 | M199: Australia | N199: Cryptocurrency | O199: German | P199: 28 | Q199: 3.3 | R199: FALSE | S199: Active | T199: 1926 | U199: Desktop | V199: 55+ | W199: Morning | X199: =D199-C199 -> 314 | Y199: {=_xlfn.IFS(E199=7.99,"BASIC",E199=11.99,"STANDARD",E199=15.99,"PREMIUM")} -> BASIC | Z199: =F199/(X199/7) -> 8.0031847 | AA199: {=_xlfn.IFS( (F199/(X199/7)) < 5, "Casual", AND((F199/(X199/7)) >= 5, (F199/(X199/7)) < 15), "Regular", (F199/(X199/7)) >= 15, "Power" )} -> Regular | AB199: =(F199/(K199+L199)) -> 0.93005181 | AC199: =IF(F199/(K199+L199) < 0.15," Browsers","Viewers") -> Viewers
A200: 6963 | B200: Chris | C200: 45113 | D200: 45625 | E200: 15.99 | F200: 172 | G200: Comedy | H200: 2 | I200: 6 | J200: FALSE | K200: 841 | L200: 83 | M200: UK | N200: PayPal | O200: French | P200: 44 | Q200: 5 | R200: TRUE | S200: Active | T200: 2933 | U200: Tablet | V200: 25-34 | W200: Evening | X200: =D200-C200 -> 512 | Y200: {=_xlfn.IFS(E200=7.99,"BASIC",E200=11.99,"STANDARD",E200=15.99,"PREMIUM")} -> PREMIUM | Z200: =F200/(X200/7) -> 2.3515625 | AA200: {=_xlfn.IFS( (F200/(X200/7)) < 5, "Casual", AND((F200/(X200/7)) >= 5, (F200/(X200/7)) < 15), "Regular", (F200/(X200/7)) >= 15, "Power" )} -> Casual | AB200: =(F200/(K200+L200)) -> 0.18614719 | AC200: =IF(F200/(K200+L200) < 0.15," Browsers","Viewers") -> Viewers
A201: 2243 | B201: Sherri | C201: 45490 | D201: 45628 | E201: 11.99 | F201: 490 | G201: Comedy | H201: 3 | I201: 3 | J201: TRUE | K201: 123 | L201: 183 | M201: France | N201: Cryptocurrency | O201: German | P201: 45 | Q201: 4.4 | R201: FALSE | S201: Active | T201: 2397 | U201: Desktop | V201: 18-24 | W201: Evening | X201: =D201-C201 -> 138 | Y201: {=_xlfn.IFS(E201=7.99,"BASIC",E201=11.99,"STANDARD",E201=15.99,"PREMIUM")} -> STANDARD | Z201: =F201/(X201/7) -> 24.855072 | AA201: {=_xlfn.IFS( (F201/(X201/7)) < 5, "Casual", AND((F201/(X201/7)) >= 5, (F201/(X201/7)) < 15), "Regular", (F201/(X201/7)) >= 15, "Power" )} -> Power | AB201: =(F201/(K201+L201)) -> 1.6013072 | AC201: =IF(F201/(K201+L201) < 0.15," Browsers","Viewers") -> Viewers
A202: 5081 | B202: Angela | C202: 45592 | D202: 45616 | E202: 11.99 | F202: 16 | G202: Romance | H202: 1 | I202: 5 | J202: TRUE | K202: 803 | L202: 196 | M202: Australia | N202: Cryptocurrency | O202: Hindi | P202: 90 | Q202: 4.3 | R202: TRUE | S202: Active | T202: 1946 | U202: Smart TV | V202: 45-54 | W202: Late Night | X202: =D202-C202 -> 24 | Y202: {=_xlfn.IFS(E202=7.99,"BASIC",E202=11.99,"STANDARD",E202=15.99,"PREMIUM")} -> STANDARD | Z202: =F202/(X202/7) -> 4.6666667 | AA202: {=_xlfn.IFS( (F202/(X202/7)) < 5, "Casual", AND((F202/(X202/7)) >= 5, (F202/(X202/7)) < 15), "Regular", (F202/(X202/7)) >= 15, "Power" )} -> Casual | AB202: =(F202/(K202+L202)) -> 0.016016016 | AC202: =IF(F202/(K202+L202) < 0.15," Browsers","Viewers") -> Browsers
A203: 4171 | B203: John | C203: 45477 | D203: 45640 | E203: 11.99 | F203: 291 | G203: Sci-Fi | H203: 2 | I203: 1 | J203: TRUE | K203: 380 | L203: 106 | M203: Canada | N203: PayPal | O203: Spanish | P203: 22 | Q203: 4.1 | R203: FALSE | S203: Active | T203: 2576 | U203: Smart TV | V203: 45-54 | W203: Evening | X203: =D203-C203 -> 163 | Y203: {=_xlfn.IFS(E203=7.99,"BASIC",E203=11.99,"STANDARD",E203=15.99,"PREMIUM")} -> STANDARD | Z203: =F203/(X203/7) -> 12.496933 | AA203: {=_xlfn.IFS( (F203/(X203/7)) < 5, "Casual", AND((F203/(X203/7)) >= 5, (F203/(X203/7)) < 15), "Regular", (F203/(X203/7)) >= 15, "Power" )} -> Regular | AB203: =(F203/(K203+L203)) -> 0.59876543 | AC203: =IF(F203/(K203+L203) < 0.15," Browsers","Viewers") -> Viewers
A204: 7399 | B204: Katherine | C204: 45517 | D204: 45635 | E204: 11.99 | F204: 119 | G204: Romance | H204: 2 | I204: 5 | J204: TRUE | K204: 344 | L204: 93 | M204: Germany | N204: Debit Card | O204: Hindi | P204: 0 | Q204: 4.2 | R204: FALSE | S204: Active | T204: 2259 | U204: Tablet | V204: 45-54 | W204: Late Night | X204: =D204-C204 -> 118 | Y204: {=_xlfn.IFS(E204=7.99,"BASIC",E204=11.99,"STANDARD",E204=15.99,"PREMIUM")} -> STANDARD | Z204: =F204/(X204/7) -> 7.059322 | AA204: {=_xlfn.IFS( (F204/(X204/7)) < 5, "Casual", AND((F204/(X204/7)) >= 5, (F204/(X204/7)) < 15), "Regular", (F204/(X204/7)) >= 15, "Power" )} -> Regular | AB204: =(F204/(K204+L204)) -> 0.27231121 | AC204: =IF(F204/(K204+L204) < 0.15," Browsers","Viewers") -> Viewers
A205: 1110 | B205: April | C205: 45417 | D205: 45630 | E205: 11.99 | F205: 35 | G205: Action | H205: 2 | I205: 3 | J205: TRUE | K205: 908 | L205: 128 | M205: USA | N205: PayPal | O205: Spanish | P205: 86 | Q205: 3.2 | R205: TRUE | S205: Active | T205: 1068 | U205: Tablet | V205: 35-44 | W205: Evening | X205: =D205-C205 -> 213 | Y205: {=_xlfn.IFS(E205=7.99,"BASIC",E205=11.99,"STANDARD",E205=15.99,"PREMIUM")} -> STANDARD | Z205: =F205/(X205/7) -> 1.1502347 | AA205: {=_xlfn.IFS( (F205/(X205/7)) < 5, "Casual", AND((F205/(X205/7)) >= 5, (F205/(X205/7)) < 15), "Regular", (F205/(X205/7)) >= 15, "Power" )} -> Casual | AB205: =(F205/(K205+L205)) -> 0.033783784 | AC205: =IF(F205/(K205+L205) < 0.15," Browsers","Viewers") -> Browsers
A206: 5630 | B206: Francis | C206: 45264 | D206: 45620 | E206: 7.99 | F206: 88 | G206: Drama | H206: 4 | I206: 6 | J206: TRUE | K206: 782 | L206: 180 | M206: USA | N206: Debit Card | O206: French | P206: 86 | Q206: 5 | R206: TRUE | S206: Active | T206: 2928 | U206: Smart TV | V206: 45-54 | W206: Late Night | X206: =D206-C206 -> 356 | Y206: {=_xlfn.IFS(E206=7.99,"BASIC",E206=11.99,"STANDARD",E206=15.99,"PREMIUM")} -> BASIC | Z206: =F206/(X206/7) -> 1.7303371 | AA206: {=_xlfn.IFS( (F206/(X206/7)) < 5, "Casual", AND((F206/(X206/7)) >= 5, (F206/(X206/7)) < 15), "Regular", (F206/(X206/7)) >= 15, "Power" )} -> Casual | AB206: =(F206/(K206+L206)) -> 0.091476091 | AC206: =IF(F206/(K206+L206) < 0.15," Browsers","Viewers") -> Browsers
... A240: 2808 | B240: Jonathan | C240: 45242 | D240: 45640 | E240: 15.99 | F240: 91 | G240: Horror | H240: 3 | I240: 6 | J240: FALSE | K240: 961 | L240: 170 | M240: USA | N240: PayPal | O240: Mandarin | P240: 87 | Q240: 4.2 | R240: FALSE | S240: Active | T240: 718 | U240: Smart TV | V240: 25-34 | W240: Afternoon | X240: =D240-C240 -> 398 | Y240: {=_xlfn.IFS(E240=7.99,"BASIC",E240=11.99,"STANDARD",E240=15.99,"PREMIUM")} -> PREMIUM | Z240: =F240/(X240/7) -> 1.6005025 | AA240: {=_xlfn.IFS( (F240/(X240/7)) < 5, "Casual", AND((F240/(X240/7)) >= 5, (F240/(X240/7)) < 15), "Regular", (F240/(X240/7)) >= 15, "Power" )} -> Casual | AB240: =(F240/(K240+L240)) -> 0.08045977 | AC240: =IF(F240/(K240+L240) < 0.15," Browsers","Viewers") -> Browsers
A241: 7484 | B241: Bradley | C241: =_xlfn.XLOOKUP(A241,'Data Anomalies -Pls Read It'!A:A,'Data Anomalies -Pls Read It'!D:D,1,0) -> 45617 | D241: =_xlfn.XLOOKUP(A241,'Data Anomalies -Pls Read It'!A:A,'Data Anomalies -Pls Read It'!C:C,1,0) -> 45634 | E241: 11.99 | F241: 152 | G241: Romance | H241: 5 | I241: 1 | J241: FALSE | K241: 623 | L241: 180 | M241: Canada | N241: Cryptocurrency | O241: French | P241: 89 | Q241: 4.5 | R241: TRUE | S241: Active | T241: 1594 | U241: Smartphone | V241: 25-34 | W241: Late Night | X241: =D241-C241 -> 17 | Y241: {=_xlfn.IFS(E241=7.99,"BASIC",E241=11.99,"STANDARD",E241=15.99,"PREMIUM")} -> STANDARD | Z241: =F241/(X241/7) -> 62.588235 | AA241: {=_xlfn.IFS( (F241/(X241/7)) < 5, "Casual", AND((F241/(X241/7)) >= 5, (F241/(X241/7)) < 15), "Regular", (F241/(X241/7)) >= 15, "Power" )} -> Power | AB241: =(F241/(K241+L241)) -> 0.18929016 | AC241: =IF(F241/(K241+L241) < 0.15," Browsers","Viewers") -> Viewers | AD241: Correction
A242: 2396 | B242: Christopher | C242: 45262 | D242: 45621 | E242: 11.99 | F242: 283 | G242: Action | H242: 3 | I242: 5 | J242: FALSE | K242: 466 | L242: 139 | M242: UK | N242: PayPal | O242: Hindi | P242: 62 | Q242: 4 | R242: TRUE | S242: Active | T242: 681 | U242: Laptop | V242: 35-44 | W242: Evening | X242: =D242-C242 -> 359 | Y242: {=_xlfn.IFS(E242=7.99,"BASIC",E242=11.99,"STANDARD",E242=15.99,"PREMIUM")} -> STANDARD | Z242: =F242/(X242/7) -> 5.5181058 | AA242: {=_xlfn.IFS( (F242/(X242/7)) < 5, "Casual", AND((F242/(X242/7)) >= 5, (F242/(X242/7)) < 15), "Regular", (F242/(X242/7)) >= 15, "Power" )} -> Regular | AB242: =(F242/(K242+L242)) -> 0.4677686 | AC242: =IF(F242/(K242+L242) < 0.15," Browsers","Viewers") -> Viewers
A243: 2472 | B243: Angela | C243: 45248 | D243: 45621 | E243: 7.99 | F243: 61 | G243: Comedy | H243: 3 | I243: 4 | J243: FALSE | K243: 860 | L243: 145 | M243: India | N243: Debit Card | O243: Spanish | P243: 82 | Q243: 4.7 | R243: TRUE | S243: Active | T243: 428 | U243: Tablet | V243: 55+ | W243: Late Night | X243: =D243-C243 -> 373 | Y243: {=_xlfn.IFS(E243=7.99,"BASIC",E243=11.99,"STANDARD",E243=15.99,"PREMIUM")} -> BASIC | Z243: =F243/(X243/7) -> 1.1447721 | AA243: {=_xlfn.IFS( (F243/(X243/7)) < 5, "Casual", AND((F243/(X243/7)) >= 5, (F243/(X243/7)) < 15), "Regular", (F243/(X243/7)) >= 15, "Power" )} -> Casual | AB243: =(F243/(K243+L243)) -> 0.060696517 | AC243: =IF(F243/(K243+L243) < 0.15," Browsers","Viewers") -> Browsers
A244: 7939 | B244: Richard | C244: 45177 | D244: 45621 | E244: 11.99 | F244: 410 | G244: Comedy | H244: 5 | I244: 6 | J244: FALSE | K244: 410 | L244: 125 | M244: France | N244: PayPal | O244: German | P244: 68 | Q244: 4.7 | R244: FALSE | S244: Active | T244: 2542 | U244: Desktop | V244: 25-34 | W244: Morning | X244: =D244-C244 -> 444 | Y244: {=_xlfn.IFS(E244=7.99,"BASIC",E244=11.99,"STANDARD",E244=15.99,"PREMIUM")} -> STANDARD | Z244: =F244/(X244/7) -> 6.463964 | AA244: {=_xlfn.IFS( (F244/(X244/7)) < 5, "Casual", AND((F244/(X244/7)) >= 5, (F244/(X244/7)) < 15), "Regular", (F244/(X244/7)) >= 15, "Power" )} -> Regular | AB244: =(F244/(K244+L244)) -> 0.76635514 | AC244: =IF(F244/(K244+L244) < 0.15," Browsers","Viewers") -> Viewers
A245: 8269 | B245: Jennifer | C245: 45348 | D245: 45643 | E245: 7.99 | F245: 88 | G245: Action | H245: 3 | I245: 1 | J245: FALSE | K245: 69 | L245: 75 | M245: India | N245: Credit Card | O245: German | P245: 80 | Q245: 4.1 | R245: FALSE | S245: Active | T245: 4763 | U245: Smart TV | V245: 55+ | W245: Evening | X245: =D245-C245 -> 295 | Y245: {=_xlfn.IFS(E245=7.99,"BASIC",E245=11.99,"STANDARD",E245=15.99,"PREMIUM")} -> BASIC | Z245: =F245/(X245/7) -> 2.0881356 | AA245: {=_xlfn.IFS( (F245/(X245/7)) < 5, "Casual", AND((F245/(X245/7)) >= 5, (F245/(X245/7)) < 15), "Regular", (F245/(X245/7)) >= 15, "Power" )} -> Casual | AB245: =(F245/(K245+L245)) -> 0.61111111 | AC245: =IF(F245/(K245+L245) < 0.15," Browsers","Viewers") -> Viewers
A246: 9073 | B246: Tiffany | C246: 45118 | D246: 45635 | E246: 15.99 | F246: 322 | G246: Documentary | H246: 3 | I246: 4 | J246: TRUE | K246: 424 | L246: 74 | M246: Australia | N246: Credit Card | O246: French | P246: 3 | Q246: 3 | R246: FALSE | S246: Active | T246: 486 | U246: Tablet | V246: 45-54 | W246: Evening | X246: =D246-C246 -> 517 | Y246: {=_xlfn.IFS(E246=7.99,"BASIC",E246=11.99,"STANDARD",E246=15.99,"PREMIUM")} -> PREMIUM | Z246: =F246/(X246/7) -> 4.3597679 | AA246: {=_xlfn.IFS( (F246/(X246/7)) < 5, "Casual", AND((F246/(X246/7)) >= 5, (F246/(X246/7)) < 15), "Regular", (F246/(X246/7)) >= 15, "Power" )} -> Casual | AB246: =(F246/(K246+L246)) -> 0.64658635 | AC246: =IF(F246/(K246+L246) < 0.15," Browsers","Viewers") -> Viewers
...

Sheet Pivot Table
C1: 1. Subscription & Revenue Analysis | L1: 2. User Engagement Metrics: | R1: 3. Demographic & Behavioral Insights: | AB1: 4. Retention & Loyalty: | AJ1: 5. Payment Preferences & Regional Trends
C2: ○ Monthly revenue based on different subscription plans. | G2: ○ Distribution of users across different price tiers. | L2: ○ Average watch hours per user & ○ Total movies vs. series watched per user. | N2: ○ Impact of recommended content on engagement. | R2: ○ Preferred genres by age group. | U2: ○ Device usage trends. | W2: ○ Peak watch time trends (Morning, Evening, Late Night). | AB2: ○ Membership status (Active vs. Inactive). & ○ Loyalty points distribution. | AE2: ○ Frequency of logins and content downloads. | AJ2: ○ Preferred payment methods by region. ○ Subscription trends by country. | AM2: ○ Language preferences and their correlation with engagement.
D4: Subscription Tier | E4: User Count | F4: Subscription Amount | H4: Subscription Tier | I4: Price | L4: Age Group | M4: No. of Movies Watched | N4: No. of Series Watched | R4: Count of User_ID | S4: Column Labels | AJ4: Subscription Tier | AK4: (All)
D5: BASIC | E5: 323 | F5: 2580.77 | H5: BASIC | I5: 7.99 | L5: 18-24 | M5: 522.77778 | N5: 109.94444 | R5: Age Group | S5: Action | T5: Comedy | U5: Documentary | V5: Drama | W5: Horror | X5: Romance | Y5: Sci-Fi | AB5: Status | AC5: Count of User_ID | AE5: Has Downloaded | AF5: Count of User_ID | AG5: Average of Watch_Hours
D6: STANDARD | E6: 345 | F6: 4136.55 | H6: STANDARD | I6: 11.99 | L6: 25-34 | M6: 502.71 | N6: 93.155 | R6: 18-24 | S6: 26 | T6: 23 | U6: 36 | V6: 25 | W6: 23 | X6: 24 | Y6: 23 | AB6: Active | AC6: 1000 | AE6: Downloaded | AF6: 499 | AG6: 257.42485 | AJ6: Count of User_ID | AK6: Column Labels
D7: PREMIUM | E7: 332 | F7: 5308.68 | H7: PREMIUM | I7: 15.99 | L7: 35-44 | M7: 532.03865 | N7: 98.801932 | R7: 25-34 | S7: 33 | T7: 29 | U7: 21 | V7: 31 | W7: 36 | X7: 27 | Y7: 23 | AB7: Grand Total | AC7: 1000 | AE7: Not Downloaded | AF7: 501 | AG7: 251.61876 | AJ7: Country Name | AK7: Credit Card | AL7: Cryptocurrency | AM7: Debit Card | AN7: PayPal
D8: Grand Total | E8: 1000 | F8: 12026 | L8: 45-54 | M8: 500.98558 | N8: 105.87981 | R8: 35-44 | S8: 32 | T8: 29 | U8: 22 | V8: 27 | W8: 34 | X8: 32 | Y8: 31 | AE8: Grand Total | AF8: 1000 | AG8: 254.516 | AJ8: Australia | AK8: 22 | AL8: 44 | AM8: 38 | AN8: 36
L9: 55+ | M9: 521.55122 | N9: 91.95122 | R9: 45-54 | S9: 34 | T9: 26 | U9: 22 | V9: 31 | W9: 32 | X9: 36 | Y9: 27 | AJ9: Canada | AK9: 34 | AL9: 27 | AM9: 36 | AN9: 42
L10: Grand Total | M10: 515.897 | N10: 99.746 | R10: 55+ | S10: 25 | T10: 39 | U10: 29 | V10: 28 | W10: 32 | X10: 27 | Y10: 25 | AB10: Loyalty Points | AC10: Count of User_ID | AJ10: France | AK10: 39 | AL10: 41 | AM10: 31 | AN10: 40
D11: Susbcription Amount | E11: Column Labels | AB11: 0-1000 | AC11: 207 | AE11: Count of User_ID | AF11: Column Labels | AJ11: Germany | AK11: 31 | AL11: 35 | AM11: 43 | AN11: 37
D12: Year & Month | E12: BASIC | F12: STANDARD | G12: PREMIUM | AB12: 1001-2000 | AC12: 215 | AE12: Avg Hrs/Wk | AF12: Not Downloaded | AG12: Downloaded | AJ12: India | AK12: 25 | AL12: 29 | AM12: 39 | AN12: 23
D13: 2022 | E13: 31.96 | F13: 95.92 | G13: 95.94 | L13: Age Group | M13: Watch Hours | R13: Device Name | S13: Users Count | T13: Count of User_ID2 | AB13: 2001-3000 | AC13: 196 | AE13: Casual (0-5 Hours) | AF13: 258 | AG13: 221 | AJ13: UK | AK13: 33 | AL13: 38 | AM13: 31 | AN13: 48
D14: Dec | E14: 31.96 | F14: 95.92 | G14: 95.94 | L14: 18-24 | M14: 237.06111 | R14: Smartphone | S14: 209 | T14: 0.209 | AB14: 3001-4000 | AC14: 191 | AE14: Power (15+ Hours) | AF14: 80 | AG14: 99 | AJ14: USA | AK14: 44 | AL14: 40 | AM14: 31 | AN14: 43
D15: 2023 | E15: 1382.27 | F15: 1978.35 | G15: 2766.27 | L15: 25-34 | M15: 268.52 | R15: Tablet | S15: 215 | T15: 0.215 | AB15: 4001-5000 | AC15: 191 | AE15: Regular (6-15 Hours) | AF15: 163 | AG15: 179 | AJ15: Grand Total | AK15: 228 | AL15: 254 | AM15: 249 | AN15: 269
D16: Jan | E16: 87.89 | F16: 119.9 | G16: 367.77 | L16: 35-44 | M16: 244.95652 | R16: Laptop | S16: 178 | T16: 0.178 | AB16: Grand Total | AC16: 1000 | AE16: Grand Total | AF16: 501 | AG16: 499
D17: Feb | E17: 95.88 | F17: 275.77 | G17: 175.89 | L17: 45-54 | M17: 255.66346 | R17: Desktop | S17: 189 | T17: 0.189
D18: Mar | E18: 127.84 | F18: 131.89 | G18: 175.89 | L18: 55+ | M18: 264.66829 | R18: Smart TV | S18: 209 | T18: 0.209 | AE18: Avg Hrs/Wk | AJ18: Count of User_ID | AK18: Column Labels
D19: Apr | E19: 175.78 | F19: 179.85 | G19: 143.91 | L19: Grand Total | M19: 254.516 | R19: Grand Total | S19: 1000 | T19: 1 | AE19: Weekly Viewing Frequency (Average Watch Hours normalized by Tenure). | AJ19: Country Name | AK19: BASIC | AL19: STANDARD | AM19: PREMIUM
D20: May | E20: 135.83 | F20: 203.83 | G20: 175.89 | AJ20: Australia | AK20: 39 | AL20: 50 | AM20: 51
D21: Jun | E21: 135.83 | F21: 143.88 | G21: 239.85 | L21: RC | AG21: Total Watch Hours | AJ21: Canada | AK21: 46 | AL21: 44 | AM21: 49
D22: Jul | E22: 87.89 | F22: 191.84 | G22: 143.91 | L22: Recommended Content | R22: Primary Watch Time | S22: Users Count | T22: Average of Watch_Hours | AE22: Avg Hrs/Wk | AF22: = | AG22: ------------------------------ | AJ22: France | AK22: 54 | AL22: 50 | AM22: 47
D23: Aug | E23: 87.89 | F23: 119.9 | G23: 175.89 | R23: Morning | S23: 222 | T23: 272.32883 | AG23: (Tenure Days)/7 | AJ23: Germany | AK23: 49 | AL23: 51 | AM23: 46
D24: Sep | E24: 111.86 | F24: 131.89 | G24: 351.78 | L24: RC Count | M24: Avg Watch Hours | R24: Afternoon | S24: 251 | T24: 247.07968 | AJ24: India | AK24: 34 | AL24: 45 | AM24: 37
D25: Oct | E25: 119.85 | F25: 155.87 | G25: 191.88 | L25: 0-20 | M25: 260.28643 | R25: Evening | S25: 256 | T25: 255.39453 | AJ25: UK | AK25: 48 | AL25: 52 | AM25: 50
D26: Nov | E26: 79.9 | F26: 143.88 | G26: 303.81 | L26: 21-40 | M26: 254.64773 | R26: Late Night | S26: 271 | T26: 245.98155 | AJ26: USA | AK26: 53 | AL26: 53 | AM26: 52
D27: Dec | E27: 135.83 | F27: 179.85 | G27: 319.8 | L27: 41-60 | M27: 247.54762 | R27: Grand Total | S27: 1000 | T27: 254.516 | AJ27: Grand Total | AK27: 323 | AL27: 345 | AM27: 332
D28: 2024 | E28: 1166.54 | F28: 2062.28 | G28: 2446.47 | L28: 61-80 | M28: 267.155
D29: Jan | E29: 103.87 | F29: 191.84 | G29: 191.88 | L29: 81-100 | M29: 244.11628
D30: Feb | E30: 103.87 | F30: 155.87 | G30: 255.84 | L30: Grand Total | M30: 254.516 | AJ30: Country Name | AK30: Users Count | AL30: Avg Watch Hours
D31: Mar | E31: 79.9 | F31: 167.86 | G31: 175.89 | AJ31: English | AK31: 168 | AL31: 248.38095
D32: Apr | E32: 95.88 | F32: 191.84 | G32: 191.88 | AJ32: French | AK32: 171 | AL32: 273.46199
D33: May | E33: 111.86 | F33: 167.86 | G33: 255.84 | AJ33: German | AK33: 167 | AL33: 244.79641
D34: Jun | E34: 95.88 | F34: 203.83 | G34: 303.81 | AJ34: Hindi | AK34: 162 | AL34: 253.35802
D35: Jul | E35: 79.9 | F35: 215.82 | G35: 191.88 | AJ35: Mandarin | AK35: 179 | AL35: 243.3352
D36: Aug | E36: 63.92 | F36: 179.85 | G36: 159.9 | AJ36: Spanish | AK36: 153 | AL36: 264.99346
D37: Sep | E37: 143.82 | F37: 179.85 | G37: 207.87 | AJ37: Grand Total | AK37: 1000 | AL37: 254.516
D38: Oct | E38: 159.8 | F38: 179.85 | G38: 175.89
D39: Nov | E39: 95.88 | F39: 107.91 | G39: 255.84
D40: Dec | E40: 31.96 | F40: 119.9 | G40: 79.95
D41: Grand Total | E41: 2580.77 | F41: 4136.55 | G41: 5308.68

Sheet Dashboard
B9: 1. Subscription & Revenue Analysis
B51: 2. User Engagement Metrics:
B87: 3. Demographic & Behavioral Insights:
B88: ='Pivot Table'!R5 -> Age Group | C88: ='Pivot Table'!S5 -> Action | D88: ='Pivot Table'!T5 -> Comedy | E88: ='Pivot Table'!U5 -> Documentary | F88: ='Pivot Table'!V5 -> Drama | G88: ='Pivot Table'!W5 -> Horror | H88: ='Pivot Table'!X5 -> Romance | I88: ='Pivot Table'!Y5 -> Sci-Fi
B89: ='Pivot Table'!R6 -> 18-24 | C89: ='Pivot Table'!S6 -> 26 | D89: ='Pivot Table'!T6 -> 23 | E89: ='Pivot Table'!U6 -> 36 | F89: ='Pivot Table'!V6 -> 25 | G89: ='Pivot Table'!W6 -> 23 | H89: ='Pivot Table'!X6 -> 24 | I89: ='Pivot Table'!Y6 -> 23
B90: ='Pivot Table'!R7 -> 25-34 | C90: ='Pivot Table'!S7 -> 33 | D90: ='Pivot Table'!T7 -> 29 | E90: ='Pivot Table'!U7 -> 21 | F90: ='Pivot Table'!V7 -> 31 | G90: ='Pivot Table'!W7 -> 36 | H90: ='Pivot Table'!X7 -> 27 | I90: ='Pivot Table'!Y7 -> 23
B91: ='Pivot Table'!R8 -> 35-44 | C91: ='Pivot Table'!S8 -> 32 | D91: ='Pivot Table'!T8 -> 29 | E91: ='Pivot Table'!U8 -> 22 | F91: ='Pivot Table'!V8 -> 27 | G91: ='Pivot Table'!W8 -> 34 | H91: ='Pivot Table'!X8 -> 32 | I91: ='Pivot Table'!Y8 -> 31
B92: ='Pivot Table'!R9 -> 45-54 | C92: ='Pivot Table'!S9 -> 34 | D92: ='Pivot Table'!T9 -> 26 | E92: ='Pivot Table'!U9 -> 22 | F92: ='Pivot Table'!V9 -> 31 | G92: ='Pivot Table'!W9 -> 32 | H92: ='Pivot Table'!X9 -> 36 | I92: ='Pivot Table'!Y9 -> 27
B93: ='Pivot Table'!R10 -> 55+ | C93: ='Pivot Table'!S10 -> 25 | D93: ='Pivot Table'!T10 -> 39 | E93: ='Pivot Table'!U10 -> 29 | F93: ='Pivot Table'!V10 -> 28 | G93: ='Pivot Table'!W10 -> 32 | H93: ='Pivot Table'!X10 -> 27 | I93: ='Pivot Table'!Y10 -> 25
C94: =C88 -> Action | D94: =D88 -> Comedy | E94: =E88 -> Documentary | F94: =F88 -> Drama | G94: =G88 -> Horror | H94: =H88 -> Romance | I94: =I88 -> Sci-Fi
B117: 4. Retention & Loyalty:
B158: 5. Payment Preferences & Regional Trends
